[{"timestamp": "2026-07-16T02:39:51.559728+00:00", "usd_krw": 1488.31, "coins": {"BTC": {"up_krw": 94750000.0, "bt_krw": 94837000.0, "cb_usd": 64570.505, "ref_usd": 64570.505}, "ETH": {"up_krw": 2822000.0, "bt_krw": 2818000.0, "cb_usd": 1920.265, "ref_usd": 1920.265}, "USDT": {"up_krw": 1467.0, "bt_krw": 1468.0, "cb_usd": 0.99933, "ref_usd": 0.99933}, "BNB": {"bt_krw": 851500.0, "cb_usd": 579.435, "ref_usd": 579.435}, "USDC": {"up_krw": 1467.0, "bt_krw": 1468.0, "cb_usd": 1.0, "ref_usd": 1.0}, "XRP": {"up_krw": 1636.0, "bt_krw": 1635.0, "cb_usd": 1.1139, "ref_usd": 1.1139}, "SOL": {"up_krw": 113000.0, "bt_krw": 113000.0, "cb_usd": 76.955, "ref_usd": 76.955}, "TRX": {"up_krw": 477.0, "bt_krw": 476.0, "cb_usd": 0.3223356886170518, "ref_usd": 0.3223356886170518}, "HYPE": {"cb_usd": 66.265, "ref_usd": 66.265}, "DOGE": {"up_krw": 108.0, "bt_krw": 109.0, "cb_usd": 0.07411, "ref_usd": 0.07411}, "USDS": {"up_krw": 1468.0, "bt_krw": 1469.0, "cb_usd": 0.9999, "ref_usd": 0.9999}, "ZEC": {"cb_usd": 565.875, "ref_usd": 565.875}, "XLM": {"up_krw": 276.0, "bt_krw": 276.0, "cb_usd": 0.1876275, "ref_usd": 0.1876275}, "LINK": {"up_krw": 12480.0, "bt_krw": 12490.0, "cb_usd": 8.4995, "ref_usd": 8.4995}, "ADA": {"up_krw": 243.0, "bt_krw": 243.0, "cb_usd": 0.16575, "ref_usd": 0.16575}, "CC": {"up_krw": 199.0, "bt_krw": 198.0, "ref_usd": 0.133709}, "DAI": {"cb_usd": 0.9997602454862492, "ref_usd": 0.9997602454862492}, "BCH": {"up_krw": 328100.0, "bt_krw": 328100.0, "cb_usd": 223.535, "ref_usd": 223.535}, "USD1": {"up_krw": 1467.0, "bt_krw": 1465.0, "cb_usd": 0.99875, "ref_usd": 0.99875}, "GRAM": {"bt_krw": 2294.0, "ref_usd": 1.541347}, "USDE": {"up_krw": 1468.0, "bt_krw": 1461.0, "ref_usd": 0.986355}, "LTC": {"cb_usd": 45.285, "ref_usd": 45.285}, "SUI": {"up_krw": 1109.0, "bt_krw": 1110.0, "cb_usd": 0.756, "ref_usd": 0.756}, "HBAR": {"up_krw": 99.5, "bt_krw": 99.44, "cb_usd": 0.067725, "ref_usd": 0.067725}, "AVAX": {"up_krw": 9840.0, "bt_krw": 9850.0, "cb_usd": 6.705, "ref_usd": 6.705}, "PYUSD": {"cb_usd": 1.0, "ref_usd": 1.0}, "NEAR": {"up_krw": 3022.0, "bt_krw": 3023.0, "cb_usd": 2.059, "ref_usd": 2.059}, "BUIDL": {"cb_usd": 1.0, "ref_usd": 1.0}, "CRO": {"up_krw": 81.6, "bt_krw": 81.5, "cb_usd": 0.055615, "ref_usd": 0.055615}, "SHIB": {"up_krw": 0.00622, "bt_krw": 0.0063, "cb_usd": 4.235e-06, "ref_usd": 4.235e-06}, "XAUT": {"up_krw": 5909000.0, "bt_krw": 5910000.0, "ref_usd": 3970.279889}, "UNI": {"up_krw": 5445.0, "bt_krw": 5400.0, "cb_usd": 3.712, "ref_usd": 3.712}, "TAO": {"up_krw": 295800.0, "bt_krw": 296800.0, "cb_usd": 201.19, "ref_usd": 201.19}, "WLFI": {"up_krw": 84.5, "bt_krw": 84.02, "cb_usd": 0.0576, "ref_usd": 0.0576}, "PAXG": {"bt_krw": 5916000.0, "cb_usd": 4019.84, "ref_usd": 4019.84}, "ONDO": {"up_krw": 541.0, "bt_krw": 541.0, "cb_usd": 0.368285, "ref_usd": 0.368285}, "DEXE": {"bt_krw": 52650.0, "cb_usd": 36.254101707871236, "ref_usd": 36.254101707871236}, "ASTER": {"bt_krw": 920.0, "cb_usd": 0.63, "ref_usd": 0.63}, "AAVE": {"up_krw": 141400.0, "bt_krw": 140200.0, "ref_usd": 95.007205}, "SKY": {"up_krw": 91.3, "bt_krw": 90.9, "ref_usd": 0.061345}, "WLD": {"up_krw": 600.0, "bt_krw": 600.0, "ref_usd": 0.403142}, "DOT": {"up_krw": 1242.0, "bt_krw": 1241.0, "ref_usd": 0.834505}, "MNT": {"up_krw": 629.0, "bt_krw": 629.0, "ref_usd": 0.422628}, "MORPHO": {"bt_krw": 3070.0, "ref_usd": 2.062745}, "ICP": {"up_krw": 3194.0, "bt_krw": 3189.0, "ref_usd": 2.146061}, "PEPE": {"up_krw": 0.0041, "bt_krw": 0.004, "ref_usd": 3e-06}, "ETC": {"up_krw": 10360.0, "bt_krw": 10370.0, "ref_usd": 6.960924}, "STABLE": {"bt_krw": 53.54, "ref_usd": 0.035974}, "POL": {"up_krw": 121.0, "bt_krw": 121.0, "ref_usd": 0.0813}, "JST": {"up_krw": 145.0, "bt_krw": 143.0, "ref_usd": 0.097426}, "ATOM": {"up_krw": 2272.0, "bt_krw": 2268.0, "ref_usd": 1.526566}, "ENA": {"up_krw": 124.0, "bt_krw": 123.0, "ref_usd": 0.083316}, "RENDER": {"up_krw": 2248.0, "bt_krw": 2226.0, "ref_usd": 1.51044}, "ALGO": {"up_krw": 125.0, "bt_krw": 124.0, "ref_usd": 0.083988}, "JUP": {"up_krw": 305.0, "bt_krw": 305.0, "ref_usd": 0.204931}, "PUMP": {"up_krw": 2.44, "bt_krw": 2.41, "ref_usd": 0.001639}, "FIL": {"up_krw": 1153.0, "bt_krw": 1140.0, "ref_usd": 0.774705}, "FLR": {"bt_krw": 9.691, "ref_usd": 0.006511}, "ARB": {"up_krw": 129.0, "bt_krw": 129.0, "ref_usd": 0.086676}, "APT": {"up_krw": 915.0, "bt_krw": 905.0, "ref_usd": 0.614792}, "INJ": {"up_krw": 7555.0, "bt_krw": 7480.0, "ref_usd": 5.076234}, "VVV": {"up_krw": 15760.0, "bt_krw": 15620.0, "ref_usd": 10.589205}, "AERO": {"up_krw": 745.0, "bt_krw": 745.0, "ref_usd": 0.500568}, "CAKE": {"bt_krw": 2047.0, "ref_usd": 1.375387}, "VET": {"up_krw": 7.17, "bt_krw": 7.095, "ref_usd": 0.004818}, "ETHFI": {"up_krw": 646.0, "bt_krw": 640.0, "ref_usd": 0.43405}, "VIRTUAL": {"up_krw": 911.0, "bt_krw": 912.0, "ref_usd": 0.612104}, "TIA": {"up_krw": 615.0, "bt_krw": 615.0, "ref_usd": 0.413221}, "PENGU": {"up_krw": 9.12, "bt_krw": 9.116, "ref_usd": 0.006128}, "PYTH": {"up_krw": 72.8, "bt_krw": 70.67, "ref_usd": 0.048915}, "TRUMP": {"up_krw": 2326.0, "bt_krw": 2322.0, "ref_usd": 1.562848}, "FET": {"bt_krw": 237.0, "ref_usd": 0.159241}, "SPX": {"up_krw": 553.0, "bt_krw": 547.0, "ref_usd": 0.371563}, "SUN": {"up_krw": 26.4, "bt_krw": 26.52, "ref_usd": 0.017738}, "CRV": {"bt_krw": 316.0, "ref_usd": 0.212322}, "SEI": {"up_krw": 71.6, "bt_krw": 70.75, "ref_usd": 0.048108}, "BONK": {"up_krw": 0.0054, "bt_krw": 0.0054, "ref_usd": 4e-06}, "STX": {"up_krw": 249.0, "bt_krw": 248.0, "ref_usd": 0.167304}, "JTO": {"up_krw": 913.0, "bt_krw": 904.0, "ref_usd": 0.613448}, "KITE": {"up_krw": 188.0, "bt_krw": 185.0, "ref_usd": 0.126318}, "GNO": {"bt_krw": 169300.0, "ref_usd": 113.753323}, "LDO": {"bt_krw": 522.0, "ref_usd": 0.350734}, "ZRO": {"up_krw": 1211.0, "bt_krw": 1204.0, "ref_usd": 0.813676}, "PENDLE": {"up_krw": 2350.0, "bt_krw": 2317.0, "ref_usd": 1.578974}, "BTT": {"up_krw": 0.0004, "bt_krw": 0.0004, "ref_usd": 0.0}, "BSV": {"up_krw": 19490.0, "bt_krw": 19390.0, "ref_usd": 13.095406}, "NFT": {"bt_krw": 0.0004, "ref_usd": 0.0}, "MON": {"up_krw": 32.7, "bt_krw": 32.33, "ref_usd": 0.021971}, "XTZ": {"up_krw": 340.0, "bt_krw": 337.0, "ref_usd": 0.228447}, "GRASS": {"bt_krw": 563.0, "ref_usd": 0.378282}, "2Z": {"up_krw": 103.0, "bt_krw": 102.0, "ref_usd": 0.069206}, "XPL": {"up_krw": 134.0, "bt_krw": 133.0, "ref_usd": 0.090035}, "CFX": {"bt_krw": 65.37, "ref_usd": 0.043922}, "OP": {"up_krw": 150.0, "bt_krw": 150.0, "ref_usd": 0.100786}, "SYRUP": {"up_krw": 283.0, "bt_krw": 280.0, "ref_usd": 0.190149}, "JASMY": {"bt_krw": 6.578, "ref_usd": 0.00442}, "FLOKI": {"bt_krw": 0.0321, "ref_usd": 2.2e-05}, "FF": {"up_krw": 98.1, "bt_krw": 97.13, "ref_usd": 0.065914}, "KAIA": {"bt_krw": 49.71, "ref_usd": 0.0334}, "STRK": {"bt_krw": 42.41, "ref_usd": 0.028495}, "GRT": {"up_krw": 26.2, "bt_krw": 26.09, "ref_usd": 0.017604}, "PIEVERSE": {"up_krw": 993.0, "bt_krw": 989.0, "ref_usd": 0.667201}, "RAY": {"up_krw": 1015.0, "bt_krw": 1001.0, "ref_usd": 0.681982}, "EIGEN": {"bt_krw": 355.0, "ref_usd": 0.238526}, "KAITO": {"up_krw": 1104.0, "bt_krw": 1095.0, "ref_usd": 0.741782}, "CHZ": {"up_krw": 24.8, "bt_krw": 24.63, "ref_usd": 0.016663}, "ENS": {"up_krw": 6380.0, "bt_krw": 6395.0, "ref_usd": 4.286747}, "AXS": {"up_krw": 1467.0, "bt_krw": 1452.0, "ref_usd": 0.985683}, "AKT": {"up_krw": 855.0, "bt_krw": 853.0, "ref_usd": 0.574478}, "IOTA": {"up_krw": 54.0, "bt_krw": 53.74, "ref_usd": 0.036283}, "COMP": {"up_krw": 24940.0, "bt_krw": 24720.0, "ref_usd": 16.757282}, "APE": {"bt_krw": 225.0, "ref_usd": 0.151178}, "WIF": {"up_krw": 224.0, "bt_krw": 222.0, "ref_usd": 0.150506}, "EDGE": {"bt_krw": 97.8, "ref_usd": 0.065712}}}]