[{"timestamp": "2026-05-07T00:48:18.369342+00:00", "usd_krw": 1447.35, "coins": {"BTC": {"up_krw": 118762000.0, "bt_krw": 118801000.0, "cb_usd": 81047.165, "ref_usd": 81047.165}, "ETH": {"up_krw": 3421000.0, "bt_krw": 3424000.0, "cb_usd": 2335.655, "ref_usd": 2335.655}, "USDT": {"up_krw": 1465.0, "bt_krw": 1465.0, "cb_usd": 0.999775, "ref_usd": 0.999775}, "XRP": {"up_krw": 2080.0, "bt_krw": 2080.0, "cb_usd": 1.41855, "ref_usd": 1.41855}, "BNB": {"bt_krw": 947000.0, "cb_usd": 645.08, "ref_usd": 645.08}, "USDC": {"up_krw": 1464.0, "bt_krw": 1465.0, "cb_usd": 1.0, "ref_usd": 1.0}, "SOL": {"up_krw": 129500.0, "bt_krw": 129500.0, "cb_usd": 88.36, "ref_usd": 88.36}, "TRX": {"up_krw": 508.0, "bt_krw": 509.0, "cb_usd": 0.3460563622894803, "ref_usd": 0.3460563622894803}, "DOGE": {"up_krw": 163.0, "bt_krw": 163.0, "cb_usd": 0.111505, "ref_usd": 0.111505}, "USDS": {"up_krw": 1468.0, "bt_krw": 1471.0, "cb_usd": 0.99985, "ref_usd": 0.99985}, "HYPE": {"cb_usd": 42.91, "ref_usd": 42.91}, "ADA": {"up_krw": 388.0, "bt_krw": 389.0, "cb_usd": 0.26545, "ref_usd": 0.26545}, "BCH": {"up_krw": 681000.0, "bt_krw": 680500.0, "cb_usd": 464.665, "ref_usd": 464.665}, "ZEC": {"cb_usd": 548.64, "ref_usd": 548.64}, "LINK": {"up_krw": 14540.0, "bt_krw": 14540.0, "cb_usd": 9.928, "ref_usd": 9.928}, "TON": {"bt_krw": 3567.0, "cb_usd": 2.434, "ref_usd": 2.434}, "CC": {"up_krw": 215.0, "ref_usd": 0.148547}, "XLM": {"up_krw": 237.0, "bt_krw": 237.0, "cb_usd": 0.1606635, "ref_usd": 0.1606635}, "USD1": {"up_krw": 1464.0, "bt_krw": 1465.0, "cb_usd": 0.99955, "ref_usd": 0.99955}, "DAI": {"cb_usd": 0.9998974185537025, "ref_usd": 0.9998974185537025}, "LTC": {"cb_usd": 56.475, "ref_usd": 56.475}, "AVAX": {"up_krw": 13980.0, "bt_krw": 13970.0, "cb_usd": 9.525, "ref_usd": 9.525}, "USDE": {"up_krw": 1468.0, "bt_krw": 1461.0, "cb_usd": 1.0000348214964412, "ref_usd": 1.0000348214964412}, "SUI": {"up_krw": 1438.0, "bt_krw": 1439.0, "cb_usd": 0.98185, "ref_usd": 0.98185}, "HBAR": {"up_krw": 132.0, "bt_krw": 133.0, "cb_usd": 0.09049, "ref_usd": 0.09049}, "SHIB": {"up_krw": 0.00928, "bt_krw": 0.0093, "cb_usd": 6.33e-06, "ref_usd": 6.33e-06}, "PYUSD": {"cb_usd": 1.0, "ref_usd": 1.0}, "CRO": {"up_krw": 103.0, "bt_krw": 103.0, "cb_usd": 0.07065, "ref_usd": 0.07065}, "TAO": {"up_krw": 453400.0, "bt_krw": 450500.0, "cb_usd": 309.295, "ref_usd": 309.295}, "XAUT": {"up_krw": 6850000.0, "bt_krw": 6840000.0, "ref_usd": 4732.777237}, "BUIDL": {"cb_usd": 1.0, "ref_usd": 1.0}, "PAXG": {"bt_krw": 6853000.0, "cb_usd": 4676.655, "ref_usd": 4676.655}, "DOT": {"up_krw": 1912.0, "bt_krw": 1915.0, "cb_usd": 1.3065, "ref_usd": 1.3065}, "MNT": {"up_krw": 968.0, "bt_krw": 969.0, "ref_usd": 0.668807}, "UNI": {"up_krw": 5040.0, "bt_krw": 5030.0, "cb_usd": 3.436, "ref_usd": 3.436}, "WLFI": {"up_krw": 98.1, "bt_krw": 98.25, "cb_usd": 0.06707, "ref_usd": 0.06707}, "NEAR": {"up_krw": 2170.0, "bt_krw": 2166.0, "cb_usd": 1.4825, "ref_usd": 1.4825}, "SKY": {"up_krw": 116.0, "bt_krw": 117.0, "cb_usd": 0.07939, "ref_usd": 0.07939}, "USDF": {"cb_usd": 1.0, "ref_usd": 1.0}, "ASTER": {"bt_krw": 987.0, "ref_usd": 0.681934}, "PEPE": {"up_krw": 0.00602, "bt_krw": 0.0061, "ref_usd": 4e-06}, "ICP": {"up_krw": 4486.0, "bt_krw": 4484.0, "ref_usd": 3.099451}, "ONDO": {"up_krw": 465.0, "bt_krw": 467.0, "ref_usd": 0.321276}, "ETC": {"up_krw": 13560.0, "bt_krw": 13570.0, "ref_usd": 9.368826}, "AAVE": {"up_krw": 136600.0, "bt_krw": 136600.0, "ref_usd": 94.379178}, "MORPHO": {"bt_krw": 3260.0, "ref_usd": 2.252387}, "ENA": {"up_krw": 174.0, "bt_krw": 174.0, "ref_usd": 0.120219}, "ALGO": {"up_krw": 174.0, "bt_krw": 175.0, "ref_usd": 0.120219}, "POL": {"up_krw": 145.0, "bt_krw": 146.0, "ref_usd": 0.100183}, "RENDER": {"up_krw": 2830.0, "bt_krw": 2832.0, "ref_usd": 1.955293}, "ATOM": {"up_krw": 2782.0, "bt_krw": 2776.0, "ref_usd": 1.922129}, "WLD": {"up_krw": 372.0, "bt_krw": 372.0, "ref_usd": 0.257021}, "FIL": {"up_krw": 1591.0, "bt_krw": 1595.0, "ref_usd": 1.099248}, "APT": {"up_krw": 1482.0, "bt_krw": 1483.0, "ref_usd": 1.023938}, "ARB": {"up_krw": 185.0, "bt_krw": 185.0, "ref_usd": 0.12782}, "STABLE": {"bt_krw": 49.14, "ref_usd": 0.033952}, "JST": {"up_krw": 127.0, "bt_krw": 128.0, "ref_usd": 0.087746}, "PUMP": {"up_krw": 2.81, "bt_krw": 2.806, "ref_usd": 0.001941}, "FLR": {"bt_krw": 11.42, "ref_usd": 0.00789}, "PENGU": {"up_krw": 15.5, "bt_krw": 15.47, "ref_usd": 0.010709}, "VET": {"up_krw": 11.2, "bt_krw": 11.21, "ref_usd": 0.007738}, "JUP": {"up_krw": 288.0, "bt_krw": 289.0, "ref_usd": 0.198984}, "BONK": {"up_krw": 0.00979, "bt_krw": 0.0098, "ref_usd": 7e-06}, "VVV": {"bt_krw": 18630.0, "ref_usd": 12.871772}, "VIRTUAL": {"up_krw": 1259.0, "bt_krw": 1259.0, "ref_usd": 0.869864}, "TRUMP": {"up_krw": 3442.0, "bt_krw": 3447.0, "ref_usd": 2.378134}, "DEXE": {"bt_krw": 16850.0, "ref_usd": 11.641941}, "CAKE": {"bt_krw": 2315.0, "ref_usd": 1.599471}, "FET": {"bt_krw": 327.0, "ref_usd": 0.22593}, "STX": {"up_krw": 368.0, "bt_krw": 368.0, "ref_usd": 0.254257}, "CHZ": {"up_krw": 62.7, "bt_krw": 62.74, "ref_usd": 0.04332}, "AERO": {"up_krw": 672.0, "bt_krw": 676.0, "ref_usd": 0.464296}, "XTZ": {"up_krw": 556.0, "bt_krw": 558.0, "ref_usd": 0.38415}, "SEI": {"up_krw": 89.2, "bt_krw": 89.22, "ref_usd": 0.06163}, "SUN": {"up_krw": 29.5, "bt_krw": 29.42, "ref_usd": 0.020382}, "INJ": {"up_krw": 5670.0, "bt_krw": 5655.0, "ref_usd": 3.917496}, "MON": {"up_krw": 46.6, "bt_krw": 46.48, "ref_usd": 0.032197}, "ZRO": {"up_krw": 2163.0, "bt_krw": 2156.0, "ref_usd": 1.494452}, "CRV": {"bt_krw": 362.0, "ref_usd": 0.250112}, "H": {"bt_krw": 294.0, "ref_usd": 0.203129}, "ETHFI": {"up_krw": 631.0, "bt_krw": 634.0, "ref_usd": 0.435968}, "GNO": {"bt_krw": 194000.0, "ref_usd": 134.037779}, "TIA": {"up_krw": 554.0, "bt_krw": 555.0, "ref_usd": 0.382768}, "PENDLE": {"up_krw": 2879.0, "bt_krw": 2868.0, "ref_usd": 1.989148}, "LDO": {"bt_krw": 564.0, "ref_usd": 0.389677}, "2Z": {"up_krw": 137.0, "bt_krw": 138.0, "ref_usd": 0.094656}, "BSV": {"up_krw": 23800.0, "bt_krw": 23800.0, "ref_usd": 16.44381}, "CFX": {"bt_krw": 92.09, "ref_usd": 0.063626}, "BTT": {"up_krw": 0.000482, "bt_krw": 0.0005, "ref_usd": 0.0}, "NFT": {"bt_krw": 0.0004, "ref_usd": 0.0}, "FLOKI": {"bt_krw": 0.0486, "ref_usd": 3.4e-05}, "OP": {"up_krw": 208.0, "bt_krw": 207.0, "ref_usd": 0.143711}, "PYTH": {"up_krw": 74.7, "bt_krw": 74.71, "ref_usd": 0.051611}, "SYRUP": {"up_krw": 364.0, "bt_krw": 365.0, "ref_usd": 0.251494}, "JASMY": {"bt_krw": 8.534, "ref_usd": 0.005896}, "GRT": {"up_krw": 38.3, "bt_krw": 38.59, "ref_usd": 0.026462}, "GWEI": {"bt_krw": 203.0, "ref_usd": 0.140256}, "KITE": {"up_krw": 227.0, "bt_krw": 225.0, "ref_usd": 0.156838}, "KAIA": {"bt_krw": 68.43, "ref_usd": 0.047279}, "IOTA": {"up_krw": 85.4, "bt_krw": 85.69, "ref_usd": 0.059004}, "ENS": {"up_krw": 9550.0, "bt_krw": 9550.0, "ref_usd": 6.598251}, "XPL": {"up_krw": 146.0, "bt_krw": 146.0, "ref_usd": 0.100874}, "STRK": {"bt_krw": 59.22, "ref_usd": 0.040916}, "AXS": {"up_krw": 2019.0, "bt_krw": 2010.0, "ref_usd": 1.39496}, "COMP": {"up_krw": 34460.0, "bt_krw": 34450.0, "ref_usd": 23.808979}, "WIF": {"up_krw": 321.0, "bt_krw": 319.0, "ref_usd": 0.221784}, "RAY": {"up_krw": 1168.0, "bt_krw": 1165.0, "ref_usd": 0.80699}, "GRASS": {"bt_krw": 528.0, "ref_usd": 0.364804}, "THETA": {"up_krw": 309.0, "bt_krw": 310.0, "ref_usd": 0.213493}, "NEO": {"up_krw": 4282.0, "bt_krw": 4290.0, "ref_usd": 2.958504}, "SAND": {"up_krw": 113.0, "bt_krw": 112.0, "ref_usd": 0.078074}, "XCN": {"up_krw": 7.55, "bt_krw": 7.565, "ref_usd": 0.005216}, "JTO": {"up_krw": 601.0, "bt_krw": 601.0, "ref_usd": 0.415241}, "IP": {"up_krw": 785.0, "bt_krw": 782.0, "ref_usd": 0.542369}, "S": {"bt_krw": 70.56, "ref_usd": 0.048751}, "AKT": {"up_krw": 893.0, "bt_krw": 893.0, "ref_usd": 0.616988}, "MANA": {"up_krw": 135.0, "bt_krw": 134.0, "ref_usd": 0.093274}, "WAL": {"up_krw": 111.0, "bt_krw": 111.0, "ref_usd": 0.076692}}}, {"timestamp": "2026-05-07T12:44:54.717049+00:00", "usd_krw": 1447.35, "coins": {"BTC": {"up_krw": 119035000.0, "bt_krw": 119000000.0, "cb_usd": 81043.495, "ref_usd": 81043.495}, "ETH": {"up_krw": 3426000.0, "bt_krw": 3427000.0, "cb_usd": 2332.76, "ref_usd": 2332.76}, "USDT": {"up_krw": 1467.0, "bt_krw": 1469.0, "cb_usd": 0.999905, "ref_usd": 0.999905}, "BNB": {"bt_krw": 954500.0, "cb_usd": 649.78, "ref_usd": 649.78}, "XRP": {"up_krw": 2076.0, "bt_krw": 2076.0, "cb_usd": 1.41395, "ref_usd": 1.41395}, "USDC": {"up_krw": 1469.0, "bt_krw": 1468.0, "cb_usd": 1.0, "ref_usd": 1.0}, "SOL": {"up_krw": 132000.0, "bt_krw": 132000.0, "cb_usd": 89.875, "ref_usd": 89.875}, "TRX": {"up_krw": 509.0, "bt_krw": 509.0, "cb_usd": 0.3464170799523688, "ref_usd": 0.3464170799523688}, "DOGE": {"up_krw": 164.0, "bt_krw": 164.0, "cb_usd": 0.11151, "ref_usd": 0.11151}, "USDS": {"up_krw": 1470.0, "bt_krw": 1467.0, "cb_usd": 0.99975, "ref_usd": 0.99975}, "HYPE": {"cb_usd": 42.98, "ref_usd": 42.98}, "ADA": {"up_krw": 396.0, "bt_krw": 396.0, "cb_usd": 0.26965, "ref_usd": 0.26965}, "ZEC": {"cb_usd": 580.46, "ref_usd": 580.46}, "BCH": {"up_krw": 674500.0, "bt_krw": 674000.0, "cb_usd": 459.24, "ref_usd": 459.24}, "LINK": {"up_krw": 14790.0, "bt_krw": 14800.0, "cb_usd": 10.067, "ref_usd": 10.067}, "TON": {"bt_krw": 3568.0, "cb_usd": 2.4275, "ref_usd": 2.4275}, "CC": {"up_krw": 215.0, "ref_usd": 0.148547}, "XLM": {"up_krw": 238.0, "bt_krw": 238.0, "cb_usd": 0.1615865, "ref_usd": 0.1615865}, "USD1": {"up_krw": 1467.0, "bt_krw": 1469.0, "cb_usd": 0.99955, "ref_usd": 0.99955}, "LTC": {"cb_usd": 57.335, "ref_usd": 57.335}, "DAI": {"cb_usd": 0.9998225397933068, "ref_usd": 0.9998225397933068}, "AVAX": {"up_krw": 14140.0, "bt_krw": 14150.0, "cb_usd": 9.635, "ref_usd": 9.635}, "SUI": {"up_krw": 1470.0, "bt_krw": 1471.0, "cb_usd": 1.0013, "ref_usd": 1.0013}, "HBAR": {"up_krw": 135.0, "bt_krw": 135.0, "cb_usd": 0.09158, "ref_usd": 0.09158}, "USDE": {"up_krw": 1466.0, "bt_krw": 1467.0, "cb_usd": 1.0000037387865557, "ref_usd": 1.0000037387865557}, "SHIB": {"up_krw": 0.00936, "bt_krw": 0.0094, "cb_usd": 6.38e-06, "ref_usd": 6.38e-06}, "PYUSD": {"cb_usd": 1.0, "ref_usd": 1.0}, "CRO": {"up_krw": 105.0, "bt_krw": 105.0, "cb_usd": 0.07092, "ref_usd": 0.07092}, "TAO": {"up_krw": 459900.0, "bt_krw": 459000.0, "cb_usd": 313.52, "ref_usd": 313.52}, "XAUT": {"up_krw": 6949000.0, "bt_krw": 6919000.0, "ref_usd": 4801.177959}, "BUIDL": {"cb_usd": 1.0, "ref_usd": 1.0}, "WLFI": {"up_krw": 107.0, "bt_krw": 107.0, "cb_usd": 0.0724, "ref_usd": 0.0724}, "PAXG": {"bt_krw": 6946000.0, "cb_usd": 4742.105, "ref_usd": 4742.105}, "DOT": {"up_krw": 1952.0, "bt_krw": 1955.0, "cb_usd": 1.3295, "ref_usd": 1.3295}, "UNI": {"up_krw": 5140.0, "bt_krw": 5145.0, "cb_usd": 3.5045, "ref_usd": 3.5045}, "MNT": {"up_krw": 983.0, "bt_krw": 978.0, "ref_usd": 0.679171}, "NEAR": {"up_krw": 2192.0, "bt_krw": 2188.0, "cb_usd": 1.493, "ref_usd": 1.493}, "SKY": {"up_krw": 118.0, "bt_krw": 117.0, "cb_usd": 0.08048, "ref_usd": 0.08048}, "ONDO": {"up_krw": 537.0, "bt_krw": 539.0, "ref_usd": 0.371022}, "USDF": {"cb_usd": 1.0, "ref_usd": 1.0}, "PEPE": {"up_krw": 0.00626, "bt_krw": 0.0063, "cb_usd": 4.265e-06, "ref_usd": 4.265e-06}, "ICP": {"up_krw": 4623.0, "bt_krw": 4615.0, "ref_usd": 3.194106}, "ASTER": {"bt_krw": 988.0, "ref_usd": 0.682625}, "ETC": {"up_krw": 13710.0, "bt_krw": 13710.0, "ref_usd": 9.472464}, "AAVE": {"up_krw": 138500.0, "bt_krw": 138000.0, "ref_usd": 95.691919}, "MORPHO": {"bt_krw": 3142.0, "ref_usd": 2.170859}, "ALGO": {"up_krw": 188.0, "bt_krw": 188.0, "ref_usd": 0.129892}, "ENA": {"up_krw": 184.0, "bt_krw": 184.0, "ref_usd": 0.127129}, "POL": {"up_krw": 146.0, "bt_krw": 147.0, "ref_usd": 0.100874}, "RENDER": {"up_krw": 2958.0, "bt_krw": 2951.0, "ref_usd": 2.043731}, "ATOM": {"up_krw": 2817.0, "bt_krw": 2816.0, "ref_usd": 1.946311}, "FIL": {"up_krw": 1626.0, "bt_krw": 1625.0, "ref_usd": 1.12343}, "WLD": {"up_krw": 381.0, "bt_krw": 380.0, "ref_usd": 0.263239}, "APT": {"up_krw": 1518.0, "bt_krw": 1517.0, "ref_usd": 1.048811}, "ARB": {"up_krw": 190.0, "bt_krw": 191.0, "ref_usd": 0.131274}, "STABLE": {"bt_krw": 48.82, "ref_usd": 0.033731}, "PUMP": {"up_krw": 3.04, "bt_krw": 3.024, "ref_usd": 0.0021}, "JST": {"up_krw": 124.0, "bt_krw": 125.0, "ref_usd": 0.085674}, "JUP": {"up_krw": 303.0, "bt_krw": 304.0, "ref_usd": 0.209348}, "FLR": {"bt_krw": 11.52, "ref_usd": 0.007959}, "VET": {"up_krw": 11.4, "bt_krw": 11.47, "ref_usd": 0.007876}, "PENGU": {"up_krw": 15.7, "bt_krw": 15.67, "ref_usd": 0.010847}, "VIRTUAL": {"up_krw": 1370.0, "bt_krw": 1369.0, "ref_usd": 0.946555}, "BONK": {"up_krw": 0.0102, "bt_krw": 0.0103, "ref_usd": 7e-06}, "VVV": {"bt_krw": 18880.0, "ref_usd": 13.044501}, "TRUMP": {"up_krw": 3506.0, "bt_krw": 3511.0, "ref_usd": 2.422353}, "DEXE": {"bt_krw": 17010.0, "ref_usd": 11.752488}, "FET": {"bt_krw": 335.0, "ref_usd": 0.231457}, "CAKE": {"bt_krw": 2290.0, "ref_usd": 1.582199}, "STX": {"up_krw": 379.0, "bt_krw": 378.0, "ref_usd": 0.261857}, "CHZ": {"up_krw": 64.6, "bt_krw": 64.47, "ref_usd": 0.044633}, "AERO": {"up_krw": 673.0, "bt_krw": 671.0, "ref_usd": 0.464987}, "SEI": {"up_krw": 90.9, "bt_krw": 90.92, "ref_usd": 0.062804}, "XTZ": {"up_krw": 560.0, "bt_krw": 561.0, "ref_usd": 0.386913}, "MON": {"up_krw": 49.0, "bt_krw": 49.02, "ref_usd": 0.033855}, "INJ": {"up_krw": 5785.0, "bt_krw": 5780.0, "ref_usd": 3.996951}, "SUN": {"up_krw": 29.5, "bt_krw": 29.55, "ref_usd": 0.020382}, "ZRO": {"up_krw": 2196.0, "bt_krw": 2194.0, "ref_usd": 1.517252}, "CRV": {"bt_krw": 364.0, "ref_usd": 0.251494}, "H": {"bt_krw": 294.0, "ref_usd": 0.203129}, "ETHFI": {"up_krw": 640.0, "bt_krw": 640.0, "ref_usd": 0.442186}, "KITE": {"up_krw": 235.0, "bt_krw": 234.0, "ref_usd": 0.162365}, "TIA": {"up_krw": 576.0, "bt_krw": 573.0, "ref_usd": 0.397968}, "GNO": {"bt_krw": 193800.0, "ref_usd": 133.899595}, "FLOKI": {"bt_krw": 0.0523, "ref_usd": 3.6e-05}, "CFX": {"bt_krw": 95.6, "ref_usd": 0.066052}, "LDO": {"bt_krw": 577.0, "ref_usd": 0.398659}, "BSV": {"up_krw": 23870.0, "bt_krw": 23870.0, "ref_usd": 16.492174}, "2Z": {"up_krw": 138.0, "bt_krw": 138.0, "ref_usd": 0.095346}, "BTT": {"up_krw": 0.000482, "bt_krw": 0.0005, "ref_usd": 0.0}, "PENDLE": {"up_krw": 2774.0, "bt_krw": 2778.0, "ref_usd": 1.916602}, "NFT": {"bt_krw": 0.0004, "ref_usd": 0.0}, "OP": {"up_krw": 216.0, "bt_krw": 216.0, "ref_usd": 0.149238}, "PYTH": {"up_krw": 79.1, "bt_krw": 79.04, "ref_usd": 0.054651}, "JASMY": {"bt_krw": 8.762, "ref_usd": 0.006054}, "GRT": {"up_krw": 39.1, "bt_krw": 39.07, "ref_usd": 0.027015}, "SYRUP": {"up_krw": 363.0, "bt_krw": 362.0, "ref_usd": 0.250803}, "KAIA": {"bt_krw": 69.3, "ref_usd": 0.047881}, "GWEI": {"bt_krw": 190.0, "ref_usd": 0.131274}, "XPL": {"up_krw": 154.0, "bt_krw": 153.0, "ref_usd": 0.106401}, "IOTA": {"up_krw": 86.9, "bt_krw": 86.82, "ref_usd": 0.060041}, "ENS": {"up_krw": 9770.0, "bt_krw": 9770.0, "ref_usd": 6.750253}, "STRK": {"bt_krw": 63.01, "ref_usd": 0.043535}, "AXS": {"up_krw": 2046.0, "bt_krw": 2048.0, "ref_usd": 1.413615}, "JTO": {"up_krw": 708.0, "bt_krw": 706.0, "ref_usd": 0.489169}, "COMP": {"up_krw": 34400.0, "bt_krw": 34370.0, "ref_usd": 23.767524}, "WIF": {"up_krw": 323.0, "bt_krw": 322.0, "ref_usd": 0.223166}, "RAY": {"up_krw": 1197.0, "bt_krw": 1195.0, "ref_usd": 0.827027}, "GRASS": {"bt_krw": 544.0, "ref_usd": 0.375859}, "THETA": {"up_krw": 313.0, "bt_krw": 313.0, "ref_usd": 0.216257}, "NEO": {"up_krw": 4364.0, "bt_krw": 4364.0, "ref_usd": 3.015159}, "SAND": {"up_krw": 116.0, "bt_krw": 115.0, "ref_usd": 0.080146}, "XCN": {"up_krw": 7.52, "bt_krw": 7.545, "ref_usd": 0.005196}, "IP": {"up_krw": 794.0, "bt_krw": 793.0, "ref_usd": 0.548588}, "AKT": {"up_krw": 955.0, "bt_krw": 954.0, "ref_usd": 0.659825}, "S": {"bt_krw": 72.92, "ref_usd": 0.050382}, "ZK": {"up_krw": 28.0, "bt_krw": 27.83, "ref_usd": 0.019346}, "WAL": {"up_krw": 115.0, "bt_krw": 115.0, "ref_usd": 0.079455}, "GALA": {"bt_krw": 5.575, "ref_usd": 0.003852}, "MANA": {"up_krw": 136.0, "bt_krw": 137.0, "ref_usd": 0.093965}}}]