[{"timestamp":"2026-02-18T00:02:40Z","usd_krw":1483.29,"coins":{"BTC":{"up_krw":100051000.0,"bt_krw":100042000.0,"cb_usd":67452.135},"ETH":{"up_krw":2951000.0,"bt_krw":2952000.0,"cb_usd":1990.445},"USDT":{"up_krw":1480.0,"bt_krw":1480.0,"cb_usd":0.99953},"XRP":{"up_krw":2185.0,"bt_krw":2185.0,"cb_usd":1.47295},"BNB":{"bt_krw":915000.0,"cb_usd":617.51},"USDC":{"up_krw":1481.0,"bt_krw":1481.0,"cb_usd":1.0},"SOL":{"up_krw":126100.0,"bt_krw":126100.0,"cb_usd":85.015},"TRX":{"up_krw":417.0,"bt_krw":418.0},"DOGE":{"up_krw":149.0,"bt_krw":149.0,"cb_usd":0.10056},"BCH":{"up_krw":835000.0,"bt_krw":834500.0,"cb_usd":562.91},"ADA":{"up_krw":417.0,"bt_krw":417.0,"cb_usd":0.2808},"USDS":{"bt_krw":1469.0,"cb_usd":0.99915},"HYPE":{"cb_usd":29.505},"USDE":{"up_krw":1480.0,"bt_krw":1477.0},"LINK":{"up_krw":13080.0,"bt_krw":13080.0,"cb_usd":8.8225},"XLM":{"up_krw":246.0,"bt_krw":245.0,"cb_usd":0.165552},"USD1":{"up_krw":1478.0,"bt_krw":1479.0,"cb_usd":0.99965},"ZEC":{"cb_usd":296.115},"HBAR":{"up_krw":151.0,"bt_krw":151.0,"cb_usd":0.101985},"DAI":{"cb_usd":0.99985},"LTC":{"cb_usd":53.89},"PYUSD":{"cb_usd":1.0},"AVAX":{"up_krw":13530.0,"bt_krw":13530.0,"cb_usd":9.135},"SHIB":{"up_krw":0.00964,"bt_krw":0.0097,"cb_usd":7e-06},"SUI":{"up_krw":1434.0,"bt_krw":1435.0,"cb_usd":0.9671},"TON":{"bt_krw":2113.0,"cb_usd":1.425},"CRO":{"up_krw":117.0,"bt_krw":117.0,"cb_usd":0.079225},"WLFI":{"up_krw":160.0,"bt_krw":160.0,"cb_usd":0.108075},"XAUT":{"up_krw":7179000.0,"bt_krw":7179000.0},"DOT":{"up_krw":1994.0,"bt_krw":1994.0,"cb_usd":1.3465},"PAXG":{"bt_krw":7215000.0,"cb_usd":4862.435},"UNI":{"up_krw":5215.0,"bt_krw":5220.0,"cb_usd":3.5195},"MNT":{"up_krw":939.0,"bt_krw":939.0,"cb_usd":0.00028},"AAVE":{"up_krw":187900.0,"bt_krw":187800.0,"cb_usd":126.495},"PEPE":{"up_krw":0.00651,"bt_krw":0.0065,"cb_usd":4e-06},"TAO":{"up_krw":283400.0,"bt_krw":283000.0,"cb_usd":191.605},"ASTER":{"bt_krw":1047.0,"cb_usd":0.708},"SKY":{"bt_krw":93.13,"cb_usd":0.062865},"ETC":{"up_krw":12880.0,"bt_krw":12860.0,"cb_usd":8.68},"NEAR":{"up_krw":1547.0,"bt_krw":1548.0,"cb_usd":1.043},"ONDO":{"up_krw":406.0,"bt_krw":407.0,"cb_usd":0.27444},"ICP":{"bt_krw":3520.0,"cb_usd":2.379},"PUMP":{"up_krw":3.26,"bt_krw":3.252,"cb_usd":0.002202},"POL":{"up_krw":161.0,"bt_krw":161.0,"cb_usd":0.10825},"WLD":{"up_krw":589.0,"bt_krw":589.0,"cb_usd":0.39695},"ATOM":{"up_krw":3333.0,"bt_krw":3331.0,"cb_usd":2.2415},"QNT":{"cb_usd":70.71},"ENA":{"up_krw":178.0,"bt_krw":179.0,"cb_usd":0.1204},"FLR":{"bt_krw":14.38,"cb_usd":0.009755},"ALGO":{"up_krw":137.0,"bt_krw":137.0,"cb_usd":0.09295},"MORPHO":{"bt_krw":2223.0,"cb_usd":1.5081},"TRUMP":{"up_krw":5115.0,"bt_krw":5115.0,"cb_usd":3.45},"RENDER":{"up_krw":2147.0,"bt_krw":2139.0,"cb_usd":1.446},"FIL":{"up_krw":1420.0,"bt_krw":1421.0,"cb_usd":0.9605},"APT":{"up_krw":1358.0,"bt_krw":1358.0,"cb_usd":0.91635},"VET":{"up_krw":12.0,"bt_krw":12.01,"cb_usd":0.008105},"ARB":{"up_krw":167.0,"bt_krw":167.0,"cb_usd":0.1129},"BONK":{"up_krw":0.00962,"bt_krw":0.0096,"cb_usd":6e-06},"JUP":{"up_krw":242.0,"bt_krw":244.0,"cb_usd":0.000204},"STABLE":{"bt_krw":43.02},"SEI":{"up_krw":111.0,"bt_krw":110.0,"cb_usd":0.074325},"DASH":{"cb_usd":37.275},"STX":{"up_krw":387.0,"bt_krw":386.0,"cb_usd":0.26065},"EURC":{"cb_usd":1.185085},"PENGU":{"up_krw":10.6,"bt_krw":10.58,"cb_usd":0.007135},"CAKE":{"bt_krw":1922.0,"cb_usd":1.3045},"XTZ":{"up_krw":584.0,"bt_krw":586.0,"cb_usd":0.39495},"VIRTUAL":{"up_krw":953.0,"bt_krw":954.0},"CHZ":{"up_krw":60.3,"bt_krw":60.22,"cb_usd":0.04065},"IP":{"up_krw":1721.0,"bt_krw":1715.0,"cb_usd":1.1535},"LIT":{"bt_krw":2352.0,"cb_usd":0.011346},"OP":{"up_krw":276.0,"bt_krw":277.0,"cb_usd":0.1875},"FET":{"bt_krw":253.0,"cb_usd":0.1709},"JST":{"up_krw":62.8,"bt_krw":62.7},"CRV":{"bt_krw":372.0,"cb_usd":0.25225},"KITE":{"up_krw":304.0,"bt_krw":304.0,"cb_usd":0.205475},"ETHFI":{"bt_krw":707.0,"cb_usd":0.4775},"NFT":{"bt_krw":0.0005},"GNO":{"bt_krw":190200.0,"cb_usd":128.335},"BTT":{"up_krw":0.000507,"bt_krw":0.0006},"KAIA":{"bt_krw":85.25},"H":{"bt_krw":275.0},"BSV":{"up_krw":24690.0,"bt_krw":24680.0,"cb_usd":16.810437},"SUN":{"up_krw":25.2,"bt_krw":25.3},"PYTH":{"up_krw":83.9,"bt_krw":83.74,"cb_usd":0.05665},"ZRO":{"up_krw":2345.0,"bt_krw":2347.0,"cb_usd":1.5865},"SPX":{"cb_usd":0.3415},"INJ":{"up_krw":4582.0,"bt_krw":4592.0,"cb_usd":3.0995},"PRIME":{"cb_usd":0.494},"FLOKI":{"bt_krw":0.0471,"cb_usd":3.2e-05},"TIA":{"up_krw":505.0,"bt_krw":506.0,"cb_usd":0.3407},"GRT":{"up_krw":41.1,"bt_krw":41.01,"cb_usd":0.02775},"IOTA":{"up_krw":103.0,"bt_krw":101.0},"JASMY":{"bt_krw":8.79,"cb_usd":0.005975},"AERO":{"up_krw":467.0,"bt_krw":466.0,"cb_usd":0.316035},"LDO":{"bt_krw":503.0,"cb_usd":0.34},"SYRUP":{"up_krw":362.0,"bt_krw":361.0,"cb_usd":0.24445},"CFX":{"bt_krw":80.73},"FRAX":{"bt_krw":1045.0},"2Z":{"up_krw":115.0,"bt_krw":115.0,"cb_usd":0.07764},"HNT":{"cb_usd":1.429},"STRK":{"bt_krw":71.38,"cb_usd":0.0485},"ENS":{"up_krw":9915.0,"bt_krw":9915.0,"cb_usd":6.695},"ZK":{"up_krw":32.3,"bt_krw":32.33,"cb_usd":0.02193},"MON":{"up_krw":32.8,"bt_krw":32.66,"cb_usd":0.022125},"AXS":{"up_krw":2016.0,"bt_krw":2011.0,"cb_usd":1.3695},"WIF":{"bt_krw":342.0,"cb_usd":0.2295},"SAND":{"up_krw":128.0,"bt_krw":128.0,"cb_usd":0.0858},"XPL":{"up_krw":143.0,"bt_krw":142.0,"cb_usd":0.0966},"THETA":{"up_krw":305.0,"bt_krw":306.0,"cb_usd":0.206465},"PENDLE":{"up_krw":1805.0,"bt_krw":1805.0,"cb_usd":1.218},"NEO":{"up_krw":4149.0,"bt_krw":4141.0},"FARTCOIN":{"cb_usd":0.19625},"MANA":{"up_krw":149.0,"bt_krw":149.0,"cb_usd":0.1011},"XCN":{"bt_krw":7.821,"cb_usd":0.005265},"GALA":{"bt_krw":5.97,"cb_usd":0.004042},"BAT":{"up_krw":189.0,"bt_krw":189.0,"cb_usd":0.12797},"CVX":{"cb_usd":2.0785},"VVV":{"cb_usd":4.3505},"FF":{"up_krw":118.0,"bt_krw":118.0},"COMP":{"up_krw":28250.0,"bt_krw":28250.0,"cb_usd":19.065},"S":{"bt_krw":71.92,"cb_usd":0.04871},"RAY":{"up_krw":994.0,"bt_krw":994.0,"cb_usd":0.68555},"GLM":{"up_krw":267.0,"bt_krw":268.0,"cb_usd":0.1807},"BARD":{"up_krw":1174.0,"bt_krw":1171.0,"cb_usd":0.7921},"FLUID":{"up_krw":3383.0,"bt_krw":3384.0,"cb_usd":2.289},"AWE":{"up_krw":131.0,"bt_krw":130.0}}},{"timestamp":"2026-02-18T05:39:31Z","usd_krw":1479.36,"coins":{"BTC":{"up_krw":100143000.0,"bt_krw":100171000.0,"cb_usd":67693.495},"ETH":{"up_krw":2952000.0,"bt_krw":2954000.0,"cb_usd":1998.135},"USDT":{"up_krw":1478.0,"bt_krw":1479.0,"cb_usd":0.999205},"XRP":{"up_krw":2188.0,"bt_krw":2189.0,"cb_usd":1.4798},"BNB":{"bt_krw":912000.0,"cb_usd":616.45},"USDC":{"up_krw":1478.0,"bt_krw":1479.0,"cb_usd":1.0},"SOL":{"up_krw":125500.0,"bt_krw":125600.0,"cb_usd":84.835},"TRX":{"up_krw":418.0,"bt_krw":417.0},"DOGE":{"up_krw":149.0,"bt_krw":150.0,"cb_usd":0.100895},"BCH":{"up_krw":837000.0,"bt_krw":837000.0,"cb_usd":565.78},"ADA":{"up_krw":417.0,"bt_krw":418.0,"cb_usd":0.28195},"USDS":{"bt_krw":1469.0,"cb_usd":0.9994},"HYPE":{"cb_usd":29.33},"USDE":{"up_krw":1477.0,"bt_krw":1478.0},"LINK":{"up_krw":13080.0,"bt_krw":13070.0,"cb_usd":8.846},"XLM":{"up_krw":247.0,"bt_krw":247.0,"cb_usd":0.166666},"USD1":{"up_krw":1478.0,"bt_krw":1479.0,"cb_usd":0.9992},"ZEC":{"cb_usd":292.055},"HBAR":{"up_krw":151.0,"bt_krw":151.0,"cb_usd":0.10198},"LTC":{"cb_usd":54.24},"DAI":{"cb_usd":0.99995},"PYUSD":{"cb_usd":1.0},"AVAX":{"up_krw":13400.0,"bt_krw":13400.0,"cb_usd":9.045},"SHIB":{"up_krw":0.00962,"bt_krw":0.0096,"cb_usd":7e-06},"SUI":{"up_krw":1433.0,"bt_krw":1435.0,"cb_usd":0.9698},"TON":{"bt_krw":2103.0,"cb_usd":1.4185},"CRO":{"up_krw":117.0,"bt_krw":117.0,"cb_usd":0.079195},"WLFI":{"up_krw":169.0,"bt_krw":170.0,"cb_usd":0.11485},"XAUT":{"up_krw":7269000.0,"bt_krw":7272000.0},"PAXG":{"bt_krw":7301000.0,"cb_usd":4938.4},"DOT":{"up_krw":1995.0,"bt_krw":1998.0,"cb_usd":1.3515},"UNI":{"up_krw":5235.0,"bt_krw":5235.0,"cb_usd":3.542},"MNT":{"up_krw":937.0,"bt_krw":939.0,"cb_usd":0.00028},"AAVE":{"up_krw":187000.0,"bt_krw":187200.0,"cb_usd":126.635},"PEPE":{"up_krw":0.0065,"bt_krw":0.0066,"cb_usd":4e-06},"TAO":{"up_krw":282700.0,"bt_krw":282200.0,"cb_usd":191.5},"ASTER":{"bt_krw":1052.0,"cb_usd":0.7115},"SKY":{"bt_krw":92.51,"cb_usd":0.0626},"ETC":{"up_krw":12860.0,"bt_krw":12860.0,"cb_usd":8.7},"NEAR":{"up_krw":1549.0,"bt_krw":1550.0,"cb_usd":1.047},"ONDO":{"up_krw":408.0,"bt_krw":407.0,"cb_usd":0.275305},"ICP":{"bt_krw":3502.0,"cb_usd":2.374},"PUMP":{"up_krw":3.21,"bt_krw":3.206,"cb_usd":0.002171},"POL":{"up_krw":162.0,"bt_krw":163.0,"cb_usd":0.1102},"ATOM":{"up_krw":3375.0,"bt_krw":3372.0,"cb_usd":2.282},"WLD":{"up_krw":579.0,"bt_krw":580.0,"cb_usd":0.3913},"QNT":{"cb_usd":69.81},"ENA":{"up_krw":178.0,"bt_krw":178.0,"cb_usd":0.12045},"ALGO":{"up_krw":138.0,"bt_krw":138.0,"cb_usd":0.0933},"TRUMP":{"up_krw":5245.0,"bt_krw":5240.0,"cb_usd":3.545},"FLR":{"bt_krw":14.29,"cb_usd":0.009665},"MORPHO":{"bt_krw":2195.0,"cb_usd":1.48645},"RENDER":{"up_krw":2151.0,"bt_krw":2148.0,"cb_usd":1.454},"FIL":{"up_krw":1421.0,"bt_krw":1421.0,"cb_usd":0.9615},"APT":{"up_krw":1356.0,"bt_krw":1356.0,"cb_usd":0.9177},"VET":{"up_krw":12.0,"bt_krw":12.02,"cb_usd":0.00812},"ARB":{"up_krw":167.0,"bt_krw":167.0,"cb_usd":0.11335},"BONK":{"up_krw":0.00961,"bt_krw":0.0096,"cb_usd":7e-06},"JUP":{"up_krw":242.0,"bt_krw":243.0,"cb_usd":0.000212},"STABLE":{"bt_krw":41.59},"SEI":{"up_krw":110.0,"bt_krw":111.0,"cb_usd":0.07455},"DASH":{"cb_usd":37.675},"STX":{"up_krw":388.0,"bt_krw":388.0,"cb_usd":0.2626},"EURC":{"cb_usd":1.184247},"PENGU":{"up_krw":10.6,"bt_krw":10.54,"cb_usd":0.007124},"CAKE":{"bt_krw":1929.0,"cb_usd":1.305},"XTZ":{"up_krw":587.0,"bt_krw":587.0,"cb_usd":0.39675},"VIRTUAL":{"up_krw":949.0,"bt_krw":949.0},"CHZ":{"up_krw":60.0,"bt_krw":60.05,"cb_usd":0.04075},"KITE":{"up_krw":346.0,"bt_krw":346.0,"cb_usd":0.233035},"IP":{"up_krw":1692.0,"bt_krw":1692.0,"cb_usd":1.142},"OP":{"up_krw":277.0,"bt_krw":277.0,"cb_usd":0.188},"LIT":{"bt_krw":2321.0,"cb_usd":0.014175},"FET":{"bt_krw":254.0,"cb_usd":0.17125},"JST":{"up_krw":63.4,"bt_krw":63.12},"CRV":{"bt_krw":373.0,"cb_usd":0.2519},"ETHFI":{"bt_krw":706.0,"cb_usd":0.4785},"NFT":{"bt_krw":0.0006},"BTT":{"up_krw":0.00051,"bt_krw":0.0006},"SPX":{"cb_usd":0.3633},"KAIA":{"bt_krw":85.12},"BSV":{"up_krw":24810.0,"bt_krw":24780.0,"cb_usd":16.803135},"H":{"bt_krw":267.0},"SUN":{"up_krw":25.3,"bt_krw":25.34},"GNO":{"bt_krw":183800.0,"cb_usd":123.87},"PYTH":{"up_krw":83.9,"bt_krw":83.77,"cb_usd":0.05665},"ZRO":{"up_krw":2314.0,"bt_krw":2311.0,"cb_usd":1.566},"INJ":{"up_krw":4602.0,"bt_krw":4598.0,"cb_usd":3.103},"PRIME":{"cb_usd":0.497},"FLOKI":{"bt_krw":0.047,"cb_usd":3.2e-05},"TIA":{"up_krw":509.0,"bt_krw":508.0,"cb_usd":0.34325},"IOTA":{"up_krw":102.0,"bt_krw":102.0},"GRT":{"up_krw":41.2,"bt_krw":41.07,"cb_usd":0.02785},"JASMY":{"bt_krw":8.779,"cb_usd":0.005915},"AERO":{"up_krw":469.0,"bt_krw":469.0,"cb_usd":0.31713},"LDO":{"bt_krw":505.0,"cb_usd":0.341},"CFX":{"bt_krw":80.86},"SYRUP":{"up_krw":360.0,"bt_krw":360.0,"cb_usd":0.24355},"FRAX":{"bt_krw":1045.0},"2Z":{"up_krw":117.0,"bt_krw":116.0,"cb_usd":0.07882},"STRK":{"bt_krw":71.64,"cb_usd":0.0485},"HNT":{"cb_usd":1.42},"ENS":{"up_krw":10010.0,"bt_krw":10040.0,"cb_usd":6.78},"ZK":{"up_krw":32.2,"bt_krw":32.23,"cb_usd":0.021825},"MON":{"up_krw":31.6,"bt_krw":31.49,"cb_usd":0.02141},"SAND":{"up_krw":128.0,"bt_krw":129.0,"cb_usd":0.0867},"WIF":{"bt_krw":341.0,"cb_usd":0.229},"AXS":{"up_krw":1990.0,"bt_krw":1994.0,"cb_usd":1.3455},"XPL":{"up_krw":143.0,"bt_krw":142.0,"cb_usd":0.0967},"THETA":{"up_krw":303.0,"bt_krw":304.0,"cb_usd":0.205458},"PENDLE":{"up_krw":1797.0,"bt_krw":1798.0,"cb_usd":1.217},"NEO":{"up_krw":4151.0,"bt_krw":4156.0},"CVX":{"cb_usd":2.162},"XCN":{"bt_krw":7.75,"cb_usd":0.00525},"MANA":{"up_krw":150.0,"bt_krw":149.0,"cb_usd":0.10155},"BAT":{"up_krw":190.0,"bt_krw":191.0,"cb_usd":0.12895},"FARTCOIN":{"cb_usd":0.1932},"GALA":{"bt_krw":5.985,"cb_usd":0.004045},"FF":{"up_krw":120.0,"bt_krw":121.0},"VVV":{"cb_usd":4.21855},"AWE":{"up_krw":143.0,"bt_krw":143.0},"S":{"bt_krw":71.56,"cb_usd":0.0483},"COMP":{"up_krw":27890.0,"bt_krw":27920.0,"cb_usd":18.885},"GLM":{"up_krw":268.0,"bt_krw":267.0,"cb_usd":0.1809},"FLUID":{"up_krw":3375.0,"bt_krw":3380.0,"cb_usd":2.293},"RAY":{"up_krw":964.0,"bt_krw":963.0,"cb_usd":0.65445},"BARD":{"up_krw":1103.0,"bt_krw":1107.0,"cb_usd":0.74915}}}]