[{"timestamp": "2026-07-21T02:44:57.870287+00:00", "usd_krw": 1478.63, "coins": {"BTC": {"up_krw": 95456000.0, "bt_krw": 95540000.0, "cb_usd": 65294.005, "ref_usd": 65294.005}, "ETH": {"up_krw": 2791000.0, "bt_krw": 2794000.0, "cb_usd": 1910.815, "ref_usd": 1910.815}, "USDT": {"up_krw": 1462.0, "bt_krw": 1462.0, "cb_usd": 0.99918, "ref_usd": 0.99918}, "BNB": {"bt_krw": 837500.0, "cb_usd": 572.53, "ref_usd": 572.53}, "USDC": {"up_krw": 1461.0, "bt_krw": 1464.0, "cb_usd": 1.0, "ref_usd": 1.0}, "XRP": {"up_krw": 1630.0, "bt_krw": 1631.0, "cb_usd": 1.1154, "ref_usd": 1.1154}, "SOL": {"up_krw": 113900.0, "bt_krw": 113900.0, "cb_usd": 77.94, "ref_usd": 77.94}, "TRX": {"up_krw": 476.0, "bt_krw": 477.0, "cb_usd": 0.3230583677844152, "ref_usd": 0.3230583677844152}, "HYPE": {"cb_usd": 62.43, "ref_usd": 62.43}, "DOGE": {"up_krw": 106.0, "bt_krw": 106.0, "cb_usd": 0.07237, "ref_usd": 0.07237}, "USDS": {"up_krw": 1467.0, "bt_krw": 1488.0, "cb_usd": 0.99985, "ref_usd": 0.99985}, "ZEC": {"cb_usd": 541.695, "ref_usd": 541.695}, "LINK": {"up_krw": 12540.0, "bt_krw": 12570.0, "cb_usd": 8.5855, "ref_usd": 8.5855}, "XLM": {"up_krw": 275.0, "bt_krw": 274.0, "cb_usd": 0.1872475, "ref_usd": 0.1872475}, "ADA": {"up_krw": 249.0, "bt_krw": 248.0, "cb_usd": 0.16995, "ref_usd": 0.16995}, "CC": {"up_krw": 182.0, "bt_krw": 181.0, "ref_usd": 0.123087}, "DAI": {"cb_usd": 0.9998040382081735, "ref_usd": 0.9998040382081735}, "BCH": {"up_krw": 323000.0, "bt_krw": 323500.0, "cb_usd": 221.125, "ref_usd": 221.125}, "USD1": {"up_krw": 1463.0, "bt_krw": 1461.0, "cb_usd": 0.9991, "ref_usd": 0.9991}, "USDE": {"up_krw": 1460.0, "bt_krw": 1461.0, "ref_usd": 0.987399}, "GRAM": {"bt_krw": 2088.0, "ref_usd": 1.412116}, "LTC": {"cb_usd": 47.14, "ref_usd": 47.14}, "SUI": {"up_krw": 1115.0, "bt_krw": 1118.0, "cb_usd": 0.7636, "ref_usd": 0.7636}, "HBAR": {"up_krw": 97.6, "bt_krw": 97.6, "cb_usd": 0.06677, "ref_usd": 0.06677}, "AVAX": {"up_krw": 9660.0, "bt_krw": 9660.0, "cb_usd": 6.62, "ref_usd": 6.62}, "PYUSD": {"cb_usd": 1.0, "ref_usd": 1.0}, "CRO": {"up_krw": 84.4, "bt_krw": 84.26, "cb_usd": 0.057775, "ref_usd": 0.057775}, "NEAR": {"up_krw": 2913.0, "bt_krw": 2917.0, "cb_usd": 1.994, "ref_usd": 1.994}, "BUIDL": {"cb_usd": 1.0, "ref_usd": 1.0}, "SHIB": {"up_krw": 0.00622, "bt_krw": 0.0062, "cb_usd": 4.25e-06, "ref_usd": 4.25e-06}, "XAUT": {"up_krw": 5893000.0, "bt_krw": 5903000.0, "ref_usd": 3985.439424}, "UNI": {"up_krw": 5340.0, "bt_krw": 5290.0, "cb_usd": 3.659, "ref_usd": 3.659}, "TAO": {"up_krw": 282900.0, "bt_krw": 280200.0, "cb_usd": 193.75, "ref_usd": 193.75}, "PAXG": {"bt_krw": 5837000.0, "cb_usd": 4032.48, "ref_usd": 4032.48}, "WLFI": {"up_krw": 83.1, "bt_krw": 82.77, "cb_usd": 0.056855, "ref_usd": 0.056855}, "ONDO": {"up_krw": 526.0, "bt_krw": 526.0, "cb_usd": 0.359655, "ref_usd": 0.359655}, "ASTER": {"bt_krw": 914.0, "cb_usd": 0.6305, "ref_usd": 0.6305}, "DEXE": {"bt_krw": 49240.0, "cb_usd": 34.22626084834509, "ref_usd": 34.22626084834509}, "SKY": {"up_krw": 91.3, "bt_krw": 91.12, "ref_usd": 0.061746}, "DOT": {"up_krw": 1212.0, "bt_krw": 1212.0, "ref_usd": 0.819676}, "MNT": {"up_krw": 620.0, "bt_krw": 619.0, "ref_usd": 0.419306}, "AAVE": {"up_krw": 132500.0, "bt_krw": 131500.0, "ref_usd": 89.609829}, "WLD": {"up_krw": 559.0, "bt_krw": 558.0, "ref_usd": 0.378052}, "MORPHO": {"bt_krw": 2885.0, "ref_usd": 1.951127}, "PEPE": {"up_krw": 0.00428, "bt_krw": 0.0043, "ref_usd": 3e-06}, "ICP": {"up_krw": 3233.0, "bt_krw": 3226.0, "ref_usd": 2.18648}, "ETC": {"up_krw": 10070.0, "bt_krw": 10090.0, "ref_usd": 6.810347}, "STABLE": {"bt_krw": 52.75, "ref_usd": 0.035675}, "POL": {"up_krw": 117.0, "bt_krw": 118.0, "ref_usd": 0.079127}, "JST": {"up_krw": 148.0, "bt_krw": 148.0, "ref_usd": 0.100092}, "PUMP": {"up_krw": 2.94, "bt_krw": 2.916, "ref_usd": 0.001988}, "ENA": {"up_krw": 122.0, "bt_krw": 122.0, "ref_usd": 0.082509}, "RENDER": {"up_krw": 2226.0, "bt_krw": 2197.0, "ref_usd": 1.505445}, "ATOM": {"up_krw": 2179.0, "bt_krw": 2162.0, "ref_usd": 1.473659}, "ALGO": {"up_krw": 121.0, "bt_krw": 122.0, "ref_usd": 0.081832}, "JUP": {"up_krw": 288.0, "bt_krw": 288.0, "ref_usd": 0.194775}, "ARB": {"up_krw": 131.0, "bt_krw": 130.0, "ref_usd": 0.088595}, "FIL": {"up_krw": 1075.0, "bt_krw": 1065.0, "ref_usd": 0.727023}, "FLR": {"bt_krw": 9.485, "ref_usd": 0.006415}, "VVV": {"up_krw": 17270.0, "bt_krw": 16960.0, "ref_usd": 11.679711}, "INJ": {"up_krw": 7820.0, "bt_krw": 7810.0, "ref_usd": 5.288671}, "APT": {"up_krw": 875.0, "bt_krw": 876.0, "ref_usd": 0.591763}, "CAKE": {"bt_krw": 2007.0, "ref_usd": 1.357335}, "ETHFI": {"up_krw": 663.0, "bt_krw": 655.0, "ref_usd": 0.448387}, "VIRTUAL": {"up_krw": 945.0, "bt_krw": 944.0, "ref_usd": 0.639104}, "AERO": {"up_krw": 639.0, "bt_krw": 637.0, "ref_usd": 0.432156}, "VET": {"up_krw": 6.96, "bt_krw": 6.886, "ref_usd": 0.004707}, "PENGU": {"up_krw": 9.29, "bt_krw": 9.282, "ref_usd": 0.006283}, "TRUMP": {"up_krw": 2322.0, "bt_krw": 2309.0, "ref_usd": 1.57037}, "PYTH": {"up_krw": 69.4, "bt_krw": 68.55, "ref_usd": 0.046935}, "SUN": {"up_krw": 27.5, "bt_krw": 27.33, "ref_usd": 0.018598}, "FET": {"bt_krw": 225.0, "ref_usd": 0.152168}, "TIA": {"up_krw": 525.0, "bt_krw": 526.0, "ref_usd": 0.355058}, "CRV": {"bt_krw": 310.0, "ref_usd": 0.209653}, "SPX": {"up_krw": 519.0, "bt_krw": 511.0, "ref_usd": 0.351}, "LDO": {"bt_krw": 567.0, "ref_usd": 0.383462}, "SEI": {"up_krw": 68.1, "bt_krw": 67.86, "ref_usd": 0.046056}, "STX": {"up_krw": 242.0, "bt_krw": 243.0, "ref_usd": 0.163665}, "JTO": {"up_krw": 883.0, "bt_krw": 877.0, "ref_usd": 0.597173}, "GNO": {"bt_krw": 163700.0, "ref_usd": 110.710408}, "ZRO": {"up_krw": 1154.0, "bt_krw": 1146.0, "ref_usd": 0.780451}, "BONK": {"up_krw": 0.00593, "bt_krw": 0.0048, "ref_usd": 4e-06}, "PENDLE": {"up_krw": 2359.0, "bt_krw": 2338.0, "ref_usd": 1.595393}, "BSV": {"up_krw": 19590.0, "bt_krw": 19540.0, "ref_usd": 13.248729}, "BTT": {"up_krw": 0.000396, "bt_krw": 0.0004, "ref_usd": 0.0}, "KITE": {"up_krw": 164.0, "bt_krw": 163.0, "ref_usd": 0.110913}, "MON": {"up_krw": 32.9, "bt_krw": 32.95, "ref_usd": 0.02225}, "NFT": {"bt_krw": 0.0004, "ref_usd": 0.0}, "XTZ": {"up_krw": 333.0, "bt_krw": 330.0, "ref_usd": 0.225208}, "CFX": {"bt_krw": 64.97, "ref_usd": 0.043939}, "GRASS": {"bt_krw": 533.0, "ref_usd": 0.360468}, "KAITO": {"up_krw": 1390.0, "bt_krw": 1376.0, "ref_usd": 0.940058}, "JASMY": {"bt_krw": 6.65, "ref_usd": 0.004497}, "2Z": {"up_krw": 95.0, "bt_krw": 94.0, "ref_usd": 0.064249}, "XPL": {"up_krw": 124.0, "bt_krw": 123.0, "ref_usd": 0.083861}, "SYRUP": {"up_krw": 275.0, "bt_krw": 270.0, "ref_usd": 0.185983}, "OP": {"up_krw": 137.0, "bt_krw": 137.0, "ref_usd": 0.092653}, "FLOKI": {"bt_krw": 0.0314, "ref_usd": 2.1e-05}, "STRK": {"bt_krw": 42.66, "ref_usd": 0.028851}, "RAY": {"up_krw": 1041.0, "bt_krw": 1035.0, "ref_usd": 0.704029}, "KAIA": {"bt_krw": 47.44, "ref_usd": 0.032084}, "ENS": {"up_krw": 6730.0, "bt_krw": 6750.0, "ref_usd": 4.551503}, "PIEVERSE": {"up_krw": 991.0, "bt_krw": 976.0, "ref_usd": 0.670214}, "FF": {"up_krw": 88.2, "bt_krw": 88.31, "ref_usd": 0.05965}, "GRT": {"up_krw": 24.4, "bt_krw": 24.25, "ref_usd": 0.016502}, "EIGEN": {"bt_krw": 345.0, "ref_usd": 0.233324}, "IOTA": {"up_krw": 52.8, "bt_krw": 52.37, "ref_usd": 0.035709}, "COMP": {"up_krw": 24540.0, "bt_krw": 24310.0, "ref_usd": 16.596417}, "AXS": {"up_krw": 1356.0, "bt_krw": 1343.0, "ref_usd": 0.917064}, "CHZ": {"up_krw": 22.2, "bt_krw": 22.06, "ref_usd": 0.015014}, "AKT": {"up_krw": 789.0, "bt_krw": 787.0, "ref_usd": 0.533601}, "WIF": {"up_krw": 220.0, "bt_krw": 218.0, "ref_usd": 0.148786}}}, {"timestamp": "2026-07-21T13:51:37.536589+00:00", "usd_krw": 1478.63, "coins": {"BTC": {"up_krw": 97420000.0, "bt_krw": 97413000.0, "cb_usd": 66602.905, "ref_usd": 66602.905}, "ETH": {"up_krw": 2831000.0, "bt_krw": 2831000.0, "cb_usd": 1934.25, "ref_usd": 1934.25}, "USDT": {"up_krw": 1462.0, "bt_krw": 1462.0, "cb_usd": 0.99924, "ref_usd": 0.99924}, "BNB": {"bt_krw": 842500.0, "cb_usd": 576.89, "ref_usd": 576.89}, "USDC": {"up_krw": 1462.0, "bt_krw": 1464.0, "cb_usd": 1.0, "ref_usd": 1.0}, "XRP": {"up_krw": 1669.0, "bt_krw": 1668.0, "cb_usd": 1.1404, "ref_usd": 1.1404}, "SOL": {"up_krw": 114800.0, "bt_krw": 114700.0, "cb_usd": 78.405, "ref_usd": 78.405}, "TRX": {"up_krw": 481.0, "bt_krw": 481.0, "cb_usd": 0.3234553897366785, "ref_usd": 0.3234553897366785}, "HYPE": {"cb_usd": 62.57, "ref_usd": 62.57}, "DOGE": {"up_krw": 108.0, "bt_krw": 107.0, "cb_usd": 0.07336, "ref_usd": 0.07336}, "USDS": {"up_krw": 1469.0, "bt_krw": 1480.0, "cb_usd": 0.99995, "ref_usd": 0.99995}, "ZEC": {"cb_usd": 545.395, "ref_usd": 545.395}, "XLM": {"up_krw": 283.0, "bt_krw": 283.0, "cb_usd": 0.1929615, "ref_usd": 0.1929615}, "ADA": {"up_krw": 257.0, "bt_krw": 257.0, "cb_usd": 0.17565, "ref_usd": 0.17565}, "LINK": {"up_krw": 12740.0, "bt_krw": 12750.0, "cb_usd": 8.712, "ref_usd": 8.712}, "CC": {"up_krw": 186.0, "bt_krw": 186.0, "ref_usd": 0.125792}, "DAI": {"cb_usd": 0.9998624574470034, "ref_usd": 0.9998624574470034}, "BCH": {"up_krw": 330400.0, "bt_krw": 330000.0, "cb_usd": 225.795, "ref_usd": 225.795}, "USD1": {"up_krw": 1463.0, "bt_krw": 1460.0, "cb_usd": 0.99885, "ref_usd": 0.99885}, "USDE": {"up_krw": 1463.0, "bt_krw": 1463.0, "ref_usd": 0.989428}, "GRAM": {"bt_krw": 2112.0, "ref_usd": 1.428347}, "LTC": {"cb_usd": 47.72, "ref_usd": 47.72}, "SUI": {"up_krw": 1125.0, "bt_krw": 1124.0, "cb_usd": 0.7689, "ref_usd": 0.7689}, "HBAR": {"up_krw": 101.0, "bt_krw": 101.0, "cb_usd": 0.06849, "ref_usd": 0.06849}, "AVAX": {"up_krw": 9700.0, "bt_krw": 9715.0, "cb_usd": 6.63, "ref_usd": 6.63}, "PYUSD": {"cb_usd": 1.0, "ref_usd": 1.0}, "CRO": {"up_krw": 85.9, "bt_krw": 86.05, "cb_usd": 0.05882, "ref_usd": 0.05882}, "NEAR": {"up_krw": 2905.0, "bt_krw": 2897.0, "cb_usd": 1.987, "ref_usd": 1.987}, "BUIDL": {"cb_usd": 1.0, "ref_usd": 1.0}, "SHIB": {"up_krw": 0.00625, "bt_krw": 0.0063, "cb_usd": 4.275e-06, "ref_usd": 4.275e-06}, "XAUT": {"up_krw": 5919000.0, "bt_krw": 5923000.0, "ref_usd": 4003.02324}, "UNI": {"up_krw": 5395.0, "bt_krw": 5340.0, "cb_usd": 3.69, "ref_usd": 3.69}, "ONDO": {"up_krw": 591.0, "bt_krw": 592.0, "cb_usd": 0.404895, "ref_usd": 0.404895}, "TAO": {"up_krw": 294000.0, "bt_krw": 291700.0, "cb_usd": 201.21, "ref_usd": 201.21}, "PAXG": {"bt_krw": 5910000.0, "cb_usd": 4042.99, "ref_usd": 4042.99}, "WLFI": {"up_krw": 82.8, "bt_krw": 82.71, "cb_usd": 0.05663, "ref_usd": 0.05663}, "ASTER": {"bt_krw": 913.0, "cb_usd": 0.6275, "ref_usd": 0.6275}, "SKY": {"up_krw": 93.2, "bt_krw": 93.11, "ref_usd": 0.063031}, "DOT": {"up_krw": 1253.0, "bt_krw": 1258.0, "ref_usd": 0.847405}, "AAVE": {"up_krw": 138100.0, "bt_krw": 136400.0, "ref_usd": 93.397113}, "MNT": {"up_krw": 627.0, "bt_krw": 626.0, "ref_usd": 0.42404}, "WLD": {"up_krw": 559.0, "bt_krw": 558.0, "ref_usd": 0.378052}, "MORPHO": {"bt_krw": 2932.0, "ref_usd": 1.982913}, "ICP": {"up_krw": 3265.0, "bt_krw": 3259.0, "ref_usd": 2.208121}, "PEPE": {"up_krw": 0.00426, "bt_krw": 0.0042, "ref_usd": 3e-06}, "ETC": {"up_krw": 10300.0, "bt_krw": 10300.0, "ref_usd": 6.965896}, "STABLE": {"bt_krw": 54.97, "ref_usd": 0.037176}, "POL": {"up_krw": 118.0, "bt_krw": 118.0, "ref_usd": 0.079803}, "ENA": {"up_krw": 127.0, "bt_krw": 126.0, "ref_usd": 0.08589}, "JST": {"up_krw": 148.0, "bt_krw": 146.0, "ref_usd": 0.100092}, "RENDER": {"up_krw": 2268.0, "bt_krw": 2239.0, "ref_usd": 1.53385}, "ATOM": {"up_krw": 2192.0, "bt_krw": 2183.0, "ref_usd": 1.482451}, "PUMP": {"up_krw": 2.84, "bt_krw": 2.805, "ref_usd": 0.001921}, "ALGO": {"up_krw": 124.0, "bt_krw": 124.0, "ref_usd": 0.083861}, "JUP": {"up_krw": 292.0, "bt_krw": 290.0, "ref_usd": 0.19748}, "VVV": {"up_krw": 18910.0, "bt_krw": 18690.0, "ref_usd": 12.788844}, "FIL": {"up_krw": 1096.0, "bt_krw": 1088.0, "ref_usd": 0.741225}, "ARB": {"up_krw": 132.0, "bt_krw": 132.0, "ref_usd": 0.089272}, "DEXE": {"bt_krw": 18470.0, "ref_usd": 12.491272}, "FLR": {"bt_krw": 9.598, "ref_usd": 0.006491}, "INJ": {"up_krw": 7795.0, "bt_krw": 7800.0, "ref_usd": 5.271763}, "APT": {"up_krw": 895.0, "bt_krw": 894.0, "ref_usd": 0.605289}, "CAKE": {"bt_krw": 2042.0, "ref_usd": 1.381006}, "ETHFI": {"up_krw": 660.0, "bt_krw": 651.0, "ref_usd": 0.446358}, "AERO": {"up_krw": 658.0, "bt_krw": 655.0, "ref_usd": 0.445006}, "VIRTUAL": {"up_krw": 972.0, "bt_krw": 971.0, "ref_usd": 0.657364}, "VET": {"up_krw": 7.17, "bt_krw": 7.085, "ref_usd": 0.004849}, "PENGU": {"up_krw": 9.36, "bt_krw": 9.34, "ref_usd": 0.00633}, "TRUMP": {"up_krw": 2353.0, "bt_krw": 2340.0, "ref_usd": 1.591335}, "PYTH": {"up_krw": 68.9, "bt_krw": 68.1, "ref_usd": 0.046597}, "SUN": {"up_krw": 27.3, "bt_krw": 27.44, "ref_usd": 0.018463}, "FET": {"bt_krw": 230.0, "ref_usd": 0.155549}, "TIA": {"up_krw": 532.0, "bt_krw": 533.0, "ref_usd": 0.359792}, "SPX": {"up_krw": 529.0, "bt_krw": 522.0, "ref_usd": 0.357763}, "LDO": {"bt_krw": 575.0, "ref_usd": 0.388873}, "CRV": {"bt_krw": 310.0, "ref_usd": 0.209653}, "SEI": {"up_krw": 68.9, "bt_krw": 68.66, "ref_usd": 0.046597}, "STX": {"up_krw": 246.0, "bt_krw": 245.0, "ref_usd": 0.16637}, "JTO": {"up_krw": 895.0, "bt_krw": 889.0, "ref_usd": 0.605289}, "GNO": {"bt_krw": 163600.0, "ref_usd": 110.642778}, "PENDLE": {"up_krw": 2422.0, "bt_krw": 2404.0, "ref_usd": 1.638}, "ZRO": {"up_krw": 1177.0, "bt_krw": 1174.0, "ref_usd": 0.796006}, "KITE": {"up_krw": 171.0, "bt_krw": 168.0, "ref_usd": 0.115647}, "BSV": {"up_krw": 19970.0, "bt_krw": 19950.0, "ref_usd": 13.505723}, "BONK": {"up_krw": 0.00547, "bt_krw": 0.0048, "ref_usd": 4e-06}, "MON": {"up_krw": 33.3, "bt_krw": 33.06, "ref_usd": 0.022521}, "BTT": {"up_krw": 0.000398, "bt_krw": 0.0004, "ref_usd": 0.0}, "NFT": {"bt_krw": 0.0004, "ref_usd": 0.0}, "XTZ": {"up_krw": 335.0, "bt_krw": 333.0, "ref_usd": 0.226561}, "KAITO": {"up_krw": 1462.0, "bt_krw": 1448.0, "ref_usd": 0.988751}, "CFX": {"bt_krw": 65.94, "ref_usd": 0.044595}, "GRASS": {"bt_krw": 528.0, "ref_usd": 0.357087}, "JASMY": {"bt_krw": 6.741, "ref_usd": 0.004559}, "2Z": {"up_krw": 95.3, "bt_krw": 94.3, "ref_usd": 0.064451}, "XPL": {"up_krw": 125.0, "bt_krw": 124.0, "ref_usd": 0.084538}, "OP": {"up_krw": 142.0, "bt_krw": 141.0, "ref_usd": 0.096035}, "SYRUP": {"up_krw": 277.0, "bt_krw": 272.0, "ref_usd": 0.187335}, "FLOKI": {"bt_krw": 0.0316, "ref_usd": 2.1e-05}, "STRK": {"bt_krw": 43.02, "ref_usd": 0.029094}, "RAY": {"up_krw": 1050.0, "bt_krw": 1048.0, "ref_usd": 0.710116}, "KAIA": {"bt_krw": 47.76, "ref_usd": 0.0323}, "ENS": {"up_krw": 6680.0, "bt_krw": 6680.0, "ref_usd": 4.517688}, "PIEVERSE": {"up_krw": 1016.0, "bt_krw": 1005.0, "ref_usd": 0.687121}, "GRT": {"up_krw": 24.7, "bt_krw": 24.54, "ref_usd": 0.016705}, "FF": {"up_krw": 88.1, "bt_krw": 87.99, "ref_usd": 0.059582}, "EIGEN": {"bt_krw": 342.0, "ref_usd": 0.231295}, "IOTA": {"up_krw": 54.6, "bt_krw": 54.06, "ref_usd": 0.036926}, "COMP": {"up_krw": 25370.0, "bt_krw": 25020.0, "ref_usd": 17.157746}, "AXS": {"up_krw": 1363.0, "bt_krw": 1355.0, "ref_usd": 0.921798}, "AKT": {"up_krw": 815.0, "bt_krw": 808.0, "ref_usd": 0.551185}, "CHZ": {"up_krw": 22.2, "bt_krw": 22.16, "ref_usd": 0.015014}, "WIF": {"up_krw": 224.0, "bt_krw": 222.0, "ref_usd": 0.151491}}}]