[{"timestamp": "2026-06-06T00:55:40.739901+00:00", "usd_krw": 1532.42, "coins": {"BTC": {"up_krw": 93250000.0, "bt_krw": 93176000.0, "cb_usd": 61299.315, "ref_usd": 61299.315}, "ETH": {"up_krw": 2424000.0, "bt_krw": 2425000.0, "cb_usd": 1594.285, "ref_usd": 1594.285}, "USDT": {"up_krw": 1520.0, "bt_krw": 1520.0, "cb_usd": 0.999655, "ref_usd": 0.999655}, "BNB": {"bt_krw": 877000.0, "cb_usd": 576.885, "ref_usd": 576.885}, "USDC": {"up_krw": 1521.0, "bt_krw": 1520.0, "cb_usd": 1.0, "ref_usd": 1.0}, "XRP": {"up_krw": 1686.0, "bt_krw": 1687.0, "cb_usd": 1.11005, "ref_usd": 1.11005}, "SOL": {"up_krw": 98350.0, "bt_krw": 98300.0, "cb_usd": 64.67, "ref_usd": 64.67}, "TRX": {"up_krw": 488.0, "bt_krw": 487.0, "cb_usd": 0.3202448698561749, "ref_usd": 0.3202448698561749}, "HYPE": {"cb_usd": 60.705, "ref_usd": 60.705}, "DOGE": {"up_krw": 126.0, "bt_krw": 126.0, "cb_usd": 0.08287, "ref_usd": 0.08287}, "USDS": {"up_krw": 1522.0, "bt_krw": 1511.0, "cb_usd": 0.9999, "ref_usd": 0.9999}, "XLM": {"up_krw": 310.0, "bt_krw": 310.0, "cb_usd": 0.2033865, "ref_usd": 0.2033865}, "ZEC": {"cb_usd": 390.31, "ref_usd": 390.31}, "ADA": {"up_krw": 245.0, "bt_krw": 245.0, "cb_usd": 0.16145, "ref_usd": 0.16145}, "CC": {"up_krw": 229.0, "ref_usd": 0.149437}, "LINK": {"up_krw": 11290.0, "bt_krw": 11290.0, "cb_usd": 7.431, "ref_usd": 7.431}, "USD1": {"up_krw": 1521.0, "bt_krw": 1517.0, "cb_usd": 0.99915, "ref_usd": 0.99915}, "USDE": {"up_krw": 1514.0, "bt_krw": 1518.0, "ref_usd": 0.987983}, "DAI": {"cb_usd": 0.9997506822978232, "ref_usd": 0.9997506822978232}, "BCH": {"up_krw": 326700.0, "bt_krw": 326300.0, "cb_usd": 214.505, "ref_usd": 214.505}, "TON": {"bt_krw": 2304.0, "cb_usd": 1.5345, "ref_usd": 1.5345}, "HBAR": {"up_krw": 124.0, "bt_krw": 124.0, "cb_usd": 0.081155, "ref_usd": 0.081155}, "LTC": {"cb_usd": 43.87, "ref_usd": 43.87}, "AVAX": {"up_krw": 10460.0, "bt_krw": 10480.0, "cb_usd": 6.885, "ref_usd": 6.885}, "SUI": {"up_krw": 1104.0, "bt_krw": 1104.0, "cb_usd": 0.7259, "ref_usd": 0.7259}, "PYUSD": {"cb_usd": 1.0, "ref_usd": 1.0}, "SHIB": {"up_krw": 0.007, "bt_krw": 0.007, "cb_usd": 4.605e-06, "ref_usd": 4.605e-06}, "XAUT": {"up_krw": 6557000.0, "bt_krw": 6476000.0, "ref_usd": 4278.865786}, "CRO": {"up_krw": 88.4, "bt_krw": 87.5, "cb_usd": 0.058375, "ref_usd": 0.058375}, "NEAR": {"up_krw": 3016.0, "bt_krw": 3017.0, "cb_usd": 1.986, "ref_usd": 1.986}, "BUIDL": {"cb_usd": 1.0, "ref_usd": 1.0}, "PAXG": {"bt_krw": 6482000.0, "cb_usd": 4330.42, "ref_usd": 4330.42}, "TAO": {"up_krw": 300800.0, "bt_krw": 301500.0, "cb_usd": 198.17, "ref_usd": 198.17}, "WLFI": {"up_krw": 85.7, "bt_krw": 85.67, "cb_usd": 0.0563, "ref_usd": 0.0563}, "WLD": {"up_krw": 813.0, "bt_krw": 812.0, "cb_usd": 0.53465, "ref_usd": 0.53465}, "MNT": {"up_krw": 794.0, "bt_krw": 794.0, "ref_usd": 0.518136}, "ONDO": {"up_krw": 525.0, "bt_krw": 525.0, "cb_usd": 0.345395, "ref_usd": 0.345395}, "DOT": {"up_krw": 1458.0, "bt_krw": 1455.0, "cb_usd": 0.958, "ref_usd": 0.958}, "ASTER": {"bt_krw": 930.0, "cb_usd": 0.6205, "ref_usd": 0.6205}, "UNI": {"up_krw": 3776.0, "bt_krw": 3767.0, "ref_usd": 2.464084}, "SKY": {"up_krw": 89.0, "bt_krw": 89.13, "ref_usd": 0.058078}, "ICP": {"up_krw": 3545.0, "bt_krw": 3528.0, "ref_usd": 2.313341}, "PEPE": {"up_krw": 0.00416, "bt_krw": 0.0041, "ref_usd": 3e-06}, "MORPHO": {"bt_krw": 2513.0, "ref_usd": 1.639895}, "ETC": {"up_krw": 10410.0, "bt_krw": 10400.0, "ref_usd": 6.793197}, "H": {"bt_krw": 887.0, "ref_usd": 0.578825}, "AAVE": {"up_krw": 95600.0, "bt_krw": 95050.0, "ref_usd": 62.385171}, "DEXE": {"bt_krw": 29710.0, "ref_usd": 19.387693}, "ENA": {"up_krw": 144.0, "bt_krw": 145.0, "ref_usd": 0.093969}, "RENDER": {"up_krw": 2575.0, "bt_krw": 2571.0, "ref_usd": 1.680354}, "VVV": {"up_krw": 28180.0, "bt_krw": 27920.0, "ref_usd": 18.389269}, "ATOM": {"up_krw": 2542.0, "bt_krw": 2545.0, "ref_usd": 1.658819}, "ALGO": {"up_krw": 145.0, "bt_krw": 144.0, "ref_usd": 0.094622}, "POL": {"up_krw": 120.0, "bt_krw": 121.0, "ref_usd": 0.078308}, "STABLE": {"bt_krw": 48.88, "ref_usd": 0.031897}, "JST": {"up_krw": 123.0, "bt_krw": 122.0, "ref_usd": 0.080265}, "FIL": {"up_krw": 1134.0, "bt_krw": 1129.0, "ref_usd": 0.740008}, "FLR": {"bt_krw": 10.15, "ref_usd": 0.006624}, "APT": {"up_krw": 1028.0, "bt_krw": 1017.0, "ref_usd": 0.670836}, "JUP": {"up_krw": 241.0, "bt_krw": 240.0, "ref_usd": 0.157268}, "INJ": {"up_krw": 7895.0, "bt_krw": 7785.0, "ref_usd": 5.151997}, "ARB": {"up_krw": 124.0, "bt_krw": 123.0, "ref_usd": 0.080918}, "PUMP": {"up_krw": 2.2, "bt_krw": 2.169, "ref_usd": 0.001436}, "FET": {"bt_krw": 308.0, "ref_usd": 0.20099}, "VET": {"up_krw": 7.31, "bt_krw": 7.295, "ref_usd": 0.00477}, "KITE": {"up_krw": 270.0, "bt_krw": 267.0, "ref_usd": 0.176192}, "PENGU": {"up_krw": 9.67, "bt_krw": 9.672, "ref_usd": 0.00631}, "TRUMP": {"up_krw": 2455.0, "bt_krw": 2451.0, "ref_usd": 1.602046}, "BONK": {"up_krw": 0.00661, "bt_krw": 0.0066, "ref_usd": 4e-06}, "CAKE": {"bt_krw": 1737.0, "ref_usd": 1.133505}, "VIRTUAL": {"up_krw": 865.0, "bt_krw": 866.0, "ref_usd": 0.564468}, "SUN": {"up_krw": 26.4, "bt_krw": 26.35, "ref_usd": 0.017228}, "STX": {"up_krw": 272.0, "bt_krw": 272.0, "ref_usd": 0.177498}, "SEI": {"up_krw": 72.5, "bt_krw": 72.47, "ref_usd": 0.047311}, "AERO": {"up_krw": 491.0, "bt_krw": 490.0, "ref_usd": 0.320409}, "TIA": {"up_krw": 466.0, "bt_krw": 460.0, "ref_usd": 0.304095}, "CRV": {"bt_krw": 274.0, "ref_usd": 0.178803}, "XTZ": {"up_krw": 375.0, "bt_krw": 373.0, "ref_usd": 0.244712}, "NFT": {"bt_krw": 0.0004, "ref_usd": 0.0}, "CHZ": {"up_krw": 38.6, "bt_krw": 38.41, "ref_usd": 0.025189}, "BTT": {"up_krw": 0.000401, "bt_krw": 0.0005, "ref_usd": 0.0}, "ETHFI": {"up_krw": 438.0, "bt_krw": 435.0, "ref_usd": 0.285823}, "PYTH": {"up_krw": 48.8, "bt_krw": 48.43, "ref_usd": 0.031845}, "JTO": {"up_krw": 793.0, "bt_krw": 782.0, "ref_usd": 0.517484}, "ZRO": {"up_krw": 1499.0, "bt_krw": 1487.0, "ref_usd": 0.978194}, "MON": {"up_krw": 31.7, "bt_krw": 31.61, "ref_usd": 0.020686}, "2Z": {"up_krw": 108.0, "bt_krw": 107.0, "ref_usd": 0.070477}, "BSV": {"up_krw": 18280.0, "bt_krw": 18260.0, "ref_usd": 11.92888}, "GNO": {"bt_krw": 532000.0, "ref_usd": 347.164343}, "CFX": {"bt_krw": 67.88, "ref_usd": 0.044296}, "FLOKI": {"bt_krw": 0.0359, "ref_usd": 2.3e-05}, "JASMY": {"bt_krw": 6.886, "ref_usd": 0.004494}, "KAIA": {"bt_krw": 58.07, "ref_usd": 0.037894}, "GWEI": {"bt_krw": 158.0, "ref_usd": 0.103105}, "LDO": {"bt_krw": 390.0, "ref_usd": 0.2545}, "FF": {"up_krw": 142.0, "bt_krw": 143.0, "ref_usd": 0.092664}, "GRT": {"up_krw": 30.7, "bt_krw": 30.79, "ref_usd": 0.020034}, "OP": {"up_krw": 152.0, "bt_krw": 150.0, "ref_usd": 0.09919}, "PENDLE": {"up_krw": 1875.0, "bt_krw": 1855.0, "ref_usd": 1.223559}, "STRK": {"bt_krw": 49.8, "ref_usd": 0.032498}, "GRASS": {"bt_krw": 507.0, "ref_usd": 0.33085}, "HOME": {"bt_krw": 81.99, "ref_usd": 0.053504}, "IOTA": {"up_krw": 68.3, "bt_krw": 68.27, "ref_usd": 0.04457}, "ENS": {"up_krw": 7070.0, "bt_krw": 7060.0, "ref_usd": 4.613631}, "XPL": {"up_krw": 103.0, "bt_krw": 102.0, "ref_usd": 0.067214}, "BILL": {"bt_krw": 109.0, "ref_usd": 0.07113}, "PIEVERSE": {"up_krw": 966.0, "bt_krw": 960.0, "ref_usd": 0.630377}, "AKT": {"up_krw": 887.0, "bt_krw": 873.0, "ref_usd": 0.578825}, "AXS": {"up_krw": 1433.0, "bt_krw": 1425.0, "ref_usd": 0.935125}, "COMP": {"up_krw": 24420.0, "bt_krw": 24140.0, "ref_usd": 15.935626}, "TRAC": {"up_krw": 521.0, "bt_krw": 515.0, "ref_usd": 0.339986}}}]