[{"timestamp": "2026-06-13T01:02:25.276436+00:00", "usd_krw": 1517.37, "coins": {"BTC": {"up_krw": 96021000.0, "bt_krw": 95870000.0, "cb_usd": 63595.945, "ref_usd": 63595.945}, "ETH": {"up_krw": 2517000.0, "bt_krw": 2515000.0, "cb_usd": 1667.345, "ref_usd": 1667.345}, "USDT": {"up_krw": 1508.0, "bt_krw": 1508.0, "cb_usd": 0.999435, "ref_usd": 0.999435}, "BNB": {"bt_krw": 912500.0, "cb_usd": 604.37, "ref_usd": 604.37}, "USDC": {"up_krw": 1507.0, "bt_krw": 1507.0, "cb_usd": 1.0, "ref_usd": 1.0}, "XRP": {"up_krw": 1712.0, "bt_krw": 1711.0, "cb_usd": 1.13515, "ref_usd": 1.13515}, "SOL": {"up_krw": 101100.0, "bt_krw": 101100.0, "cb_usd": 67.015, "ref_usd": 67.015}, "TRX": {"up_krw": 476.0, "bt_krw": 476.0, "cb_usd": 0.3156124862896576, "ref_usd": 0.3156124862896576}, "DOGE": {"up_krw": 130.0, "bt_krw": 129.0, "cb_usd": 0.0861, "ref_usd": 0.0861}, "HYPE": {"cb_usd": 59.3, "ref_usd": 59.3}, "USDS": {"up_krw": 1507.0, "bt_krw": 1506.0, "cb_usd": 0.99995, "ref_usd": 0.99995}, "ZEC": {"cb_usd": 416.71, "ref_usd": 416.71}, "ADA": {"up_krw": 257.0, "bt_krw": 257.0, "cb_usd": 0.16995, "ref_usd": 0.16995}, "XLM": {"up_krw": 283.0, "bt_krw": 283.0, "cb_usd": 0.1875605, "ref_usd": 0.1875605}, "CC": {"up_krw": 247.0, "ref_usd": 0.162782}, "LINK": {"up_krw": 11910.0, "bt_krw": 11910.0, "cb_usd": 7.889, "ref_usd": 7.889}, "TON": {"bt_krw": 2516.0, "cb_usd": 1.6845, "ref_usd": 1.6845}, "USDE": {"up_krw": 1510.0, "bt_krw": 1511.0, "ref_usd": 0.995146}, "USD1": {"up_krw": 1510.0, "bt_krw": 1508.0, "cb_usd": 1.0002, "ref_usd": 1.0002}, "DAI": {"cb_usd": 0.999703069053819, "ref_usd": 0.999703069053819}, "BCH": {"up_krw": 305400.0, "bt_krw": 305000.0, "cb_usd": 202.555, "ref_usd": 202.555}, "HBAR": {"up_krw": 118.0, "bt_krw": 118.0, "cb_usd": 0.077865, "ref_usd": 0.077865}, "LTC": {"cb_usd": 43.335, "ref_usd": 43.335}, "SUI": {"up_krw": 1135.0, "bt_krw": 1133.0, "cb_usd": 0.75205, "ref_usd": 0.75205}, "SHIB": {"up_krw": 0.00732, "bt_krw": 0.0074, "cb_usd": 4.855e-06, "ref_usd": 4.855e-06}, "AVAX": {"up_krw": 9955.0, "bt_krw": 9935.0, "cb_usd": 6.58, "ref_usd": 6.58}, "PYUSD": {"cb_usd": 1.0, "ref_usd": 1.0}, "CRO": {"up_krw": 89.5, "bt_krw": 89.59, "cb_usd": 0.059335, "ref_usd": 0.059335}, "NEAR": {"up_krw": 3033.0, "bt_krw": 3024.0, "cb_usd": 2.009, "ref_usd": 2.009}, "XAUT": {"up_krw": 6333000.0, "bt_krw": 6271000.0, "ref_usd": 4173.680508}, "BUIDL": {"cb_usd": 1.0, "ref_usd": 1.0}, "TAO": {"up_krw": 321700.0, "bt_krw": 320100.0, "cb_usd": 213.24, "ref_usd": 213.24}, "PAXG": {"bt_krw": 6289000.0, "cb_usd": 4208.545, "ref_usd": 4208.545}, "WLFI": {"up_krw": 87.7, "bt_krw": 87.51, "cb_usd": 0.058195, "ref_usd": 0.058195}, "MNT": {"up_krw": 813.0, "bt_krw": 806.0, "ref_usd": 0.535797}, "ONDO": {"up_krw": 538.0, "bt_krw": 536.0, "cb_usd": 0.35598, "ref_usd": 0.35598}, "ASTER": {"bt_krw": 934.0, "cb_usd": 0.629, "ref_usd": 0.629}, "DOT": {"up_krw": 1452.0, "bt_krw": 1450.0, "cb_usd": 0.963, "ref_usd": 0.963}, "WLD": {"up_krw": 719.0, "bt_krw": 719.0, "ref_usd": 0.473848}, "UNI": {"up_krw": 3759.0, "bt_krw": 3766.0, "ref_usd": 2.47732}, "SKY": {"up_krw": 84.9, "bt_krw": 84.82, "ref_usd": 0.055952}, "ICP": {"up_krw": 3550.0, "bt_krw": 3538.0, "ref_usd": 2.339581}, "MORPHO": {"bt_krw": 2945.0, "ref_usd": 1.940864}, "PEPE": {"up_krw": 0.00425, "bt_krw": 0.0043, "ref_usd": 3e-06}, "ETC": {"up_krw": 10810.0, "bt_krw": 10810.0, "ref_usd": 7.124189}, "ATOM": {"up_krw": 3029.0, "bt_krw": 3026.0, "ref_usd": 1.996223}, "AAVE": {"up_krw": 96950.0, "bt_krw": 97000.0, "ref_usd": 63.893625}, "DEXE": {"bt_krw": 28810.0, "ref_usd": 18.986852}, "RENDER": {"up_krw": 2537.0, "bt_krw": 2522.0, "ref_usd": 1.671977}, "STABLE": {"bt_krw": 52.94, "ref_usd": 0.034889}, "POL": {"up_krw": 113.0, "bt_krw": 112.0, "ref_usd": 0.074471}, "ALGO": {"up_krw": 132.0, "bt_krw": 132.0, "ref_usd": 0.086993}, "ENA": {"up_krw": 118.0, "bt_krw": 118.0, "ref_usd": 0.077766}, "FLR": {"bt_krw": 11.8, "ref_usd": 0.007777}, "VVV": {"up_krw": 21450.0, "bt_krw": 21300.0, "ref_usd": 14.136341}, "JST": {"up_krw": 115.0, "bt_krw": 113.0, "ref_usd": 0.075789}, "FIL": {"up_krw": 1142.0, "bt_krw": 1140.0, "ref_usd": 0.75262}, "JUP": {"up_krw": 251.0, "bt_krw": 250.0, "ref_usd": 0.165418}, "APT": {"up_krw": 971.0, "bt_krw": 968.0, "ref_usd": 0.639925}, "PUMP": {"up_krw": 2.28, "bt_krw": 2.251, "ref_usd": 0.001503}, "ARB": {"up_krw": 127.0, "bt_krw": 127.0, "ref_usd": 0.083698}, "INJ": {"up_krw": 7795.0, "bt_krw": 7735.0, "ref_usd": 5.137192}, "TRUMP": {"up_krw": 3250.0, "bt_krw": 3249.0, "ref_usd": 2.14187}, "CAKE": {"bt_krw": 1959.0, "ref_usd": 1.291053}, "KITE": {"up_krw": 289.0, "bt_krw": 284.0, "ref_usd": 0.190462}, "VET": {"up_krw": 7.59, "bt_krw": 7.582, "ref_usd": 0.005002}, "PENGU": {"up_krw": 10.2, "bt_krw": 10.14, "ref_usd": 0.006722}, "FET": {"bt_krw": 282.0, "ref_usd": 0.185848}, "H": {"bt_krw": 240.0, "ref_usd": 0.158169}, "VIRTUAL": {"up_krw": 925.0, "bt_krw": 924.0, "ref_usd": 0.609609}, "GWEI": {"bt_krw": 278.0, "ref_usd": 0.183212}, "BONK": {"up_krw": 0.00664, "bt_krw": 0.0067, "ref_usd": 4e-06}, "CRV": {"bt_krw": 357.0, "ref_usd": 0.235276}, "SEI": {"up_krw": 79.1, "bt_krw": 78.91, "ref_usd": 0.05213}, "AERO": {"up_krw": 539.0, "bt_krw": 537.0, "ref_usd": 0.355221}, "STX": {"up_krw": 273.0, "bt_krw": 272.0, "ref_usd": 0.179917}, "SUN": {"up_krw": 25.5, "bt_krw": 25.37, "ref_usd": 0.016805}, "TIA": {"up_krw": 488.0, "bt_krw": 484.0, "ref_usd": 0.32161}, "PYTH": {"up_krw": 57.9, "bt_krw": 57.7, "ref_usd": 0.038158}, "GNO": {"bt_krw": 390000.0, "ref_usd": 257.02438}, "ETHFI": {"up_krw": 470.0, "bt_krw": 466.0, "ref_usd": 0.309747}, "CHZ": {"up_krw": 39.1, "bt_krw": 38.87, "ref_usd": 0.025768}, "NFT": {"bt_krw": 0.0005, "ref_usd": 0.0}, "JTO": {"up_krw": 828.0, "bt_krw": 822.0, "ref_usd": 0.545683}, "BTT": {"up_krw": 0.000401, "bt_krw": 0.0005, "ref_usd": 0.0}, "XTZ": {"up_krw": 355.0, "bt_krw": 352.0, "ref_usd": 0.233958}, "MON": {"up_krw": 31.7, "bt_krw": 31.56, "ref_usd": 0.020891}, "FLOKI": {"bt_krw": 0.0375, "ref_usd": 2.5e-05}, "GRASS": {"bt_krw": 582.0, "ref_usd": 0.383559}, "CFX": {"bt_krw": 67.44, "ref_usd": 0.044445}, "2Z": {"up_krw": 103.0, "bt_krw": 101.0, "ref_usd": 0.067881}, "BSV": {"up_krw": 17660.0, "bt_krw": 17580.0, "ref_usd": 11.638591}, "JASMY": {"bt_krw": 6.983, "ref_usd": 0.004602}, "ZRO": {"up_krw": 1374.0, "bt_krw": 1365.0, "ref_usd": 0.905517}, "FF": {"up_krw": 120.0, "bt_krw": 119.0, "ref_usd": 0.079084}, "LDO": {"bt_krw": 389.0, "ref_usd": 0.256365}, "KAIA": {"bt_krw": 55.63, "ref_usd": 0.036662}, "GRT": {"up_krw": 30.1, "bt_krw": 29.86, "ref_usd": 0.019837}, "STRK": {"bt_krw": 50.95, "ref_usd": 0.033578}, "OP": {"up_krw": 150.0, "bt_krw": 150.0, "ref_usd": 0.098856}, "PENDLE": {"up_krw": 1890.0, "bt_krw": 1882.0, "ref_usd": 1.24558}, "XPL": {"up_krw": 128.0, "bt_krw": 127.0, "ref_usd": 0.084357}, "IOTA": {"up_krw": 70.0, "bt_krw": 69.21, "ref_usd": 0.046133}, "ENS": {"up_krw": 7320.0, "bt_krw": 7300.0, "ref_usd": 4.82415}, "PIEVERSE": {"up_krw": 1033.0, "bt_krw": 1031.0, "ref_usd": 0.680785}, "BILL": {"bt_krw": 110.0, "ref_usd": 0.072494}, "AKT": {"up_krw": 918.0, "bt_krw": 913.0, "ref_usd": 0.604996}, "COMP": {"up_krw": 26260.0, "bt_krw": 26080.0, "ref_usd": 17.306308}, "AXS": {"up_krw": 1428.0, "bt_krw": 1430.0, "ref_usd": 0.941105}, "TRAC": {"up_krw": 548.0, "bt_krw": 548.0, "ref_usd": 0.361152}, "RAY": {"up_krw": 897.0, "bt_krw": 887.0, "ref_usd": 0.591156}}}, {"timestamp": "2026-06-13T12:42:55.372209+00:00", "usd_krw": 1517.37, "coins": {"BTC": {"up_krw": 96611000.0, "bt_krw": 96528000.0, "cb_usd": 63975.445, "ref_usd": 63975.445}, "ETH": {"up_krw": 2534000.0, "bt_krw": 2532000.0, "cb_usd": 1677.385, "ref_usd": 1677.385}, "USDT": {"up_krw": 1508.0, "bt_krw": 1507.0, "cb_usd": 0.99939, "ref_usd": 0.99939}, "BNB": {"bt_krw": 915500.0, "cb_usd": 607.26, "ref_usd": 607.26}, "USDC": {"up_krw": 1510.0, "bt_krw": 1507.0, "cb_usd": 1.0, "ref_usd": 1.0}, "XRP": {"up_krw": 1736.0, "bt_krw": 1734.0, "cb_usd": 1.1495, "ref_usd": 1.1495}, "SOL": {"up_krw": 102300.0, "bt_krw": 102300.0, "cb_usd": 67.815, "ref_usd": 67.815}, "TRX": {"up_krw": 477.0, "bt_krw": 478.0, "cb_usd": 0.3167403862935111, "ref_usd": 0.3167403862935111}, "DOGE": {"up_krw": 133.0, "bt_krw": 132.0, "cb_usd": 0.088175, "ref_usd": 0.088175}, "HYPE": {"cb_usd": 58.97, "ref_usd": 58.97}, "USDS": {"up_krw": 1508.0, "bt_krw": 1528.0, "cb_usd": 0.99995, "ref_usd": 0.99995}, "ZEC": {"cb_usd": 415.46, "ref_usd": 415.46}, "ADA": {"up_krw": 261.0, "bt_krw": 261.0, "cb_usd": 0.17315, "ref_usd": 0.17315}, "XLM": {"up_krw": 286.0, "bt_krw": 286.0, "cb_usd": 0.190051, "ref_usd": 0.190051}, "CC": {"up_krw": 245.0, "ref_usd": 0.161464}, "LINK": {"up_krw": 12070.0, "bt_krw": 12060.0, "cb_usd": 7.9905, "ref_usd": 7.9905}, "TON": {"bt_krw": 2541.0, "cb_usd": 1.697, "ref_usd": 1.697}, "USDE": {"up_krw": 1503.0, "bt_krw": 1504.0, "ref_usd": 0.990532}, "USD1": {"up_krw": 1509.0, "bt_krw": 1509.0, "cb_usd": 1.0002, "ref_usd": 1.0002}, "DAI": {"cb_usd": 0.9996166060932508, "ref_usd": 0.9996166060932508}, "BCH": {"up_krw": 314200.0, "bt_krw": 313800.0, "cb_usd": 208.085, "ref_usd": 208.085}, "HBAR": {"up_krw": 119.0, "bt_krw": 119.0, "cb_usd": 0.078505, "ref_usd": 0.078505}, "LTC": {"cb_usd": 43.88, "ref_usd": 43.88}, "SUI": {"up_krw": 1158.0, "bt_krw": 1157.0, "cb_usd": 0.76695, "ref_usd": 0.76695}, "SHIB": {"up_krw": 0.00757, "bt_krw": 0.0076, "cb_usd": 5.01e-06, "ref_usd": 5.01e-06}, "AVAX": {"up_krw": 10060.0, "bt_krw": 10040.0, "cb_usd": 6.665, "ref_usd": 6.665}, "PYUSD": {"cb_usd": 1.0, "ref_usd": 1.0}, "CRO": {"up_krw": 90.6, "bt_krw": 90.57, "cb_usd": 0.06001, "ref_usd": 0.06001}, "NEAR": {"up_krw": 3093.0, "bt_krw": 3086.0, "cb_usd": 2.047, "ref_usd": 2.047}, "XAUT": {"up_krw": 6344000.0, "bt_krw": 6324000.0, "ref_usd": 4180.929913}, "BUIDL": {"cb_usd": 1.0, "ref_usd": 1.0}, "TAO": {"up_krw": 372000.0, "bt_krw": 370900.0, "cb_usd": 246.865, "ref_usd": 246.865}, "PAXG": {"bt_krw": 6304000.0, "cb_usd": 4214.57, "ref_usd": 4214.57}, "WLFI": {"up_krw": 89.1, "bt_krw": 89.14, "cb_usd": 0.059135, "ref_usd": 0.059135}, "MNT": {"up_krw": 820.0, "bt_krw": 818.0, "ref_usd": 0.54041}, "ONDO": {"up_krw": 556.0, "bt_krw": 556.0, "cb_usd": 0.368635, "ref_usd": 0.368635}, "ASTER": {"bt_krw": 950.0, "cb_usd": 0.6385, "ref_usd": 0.6385}, "WLD": {"up_krw": 750.0, "bt_krw": 750.0, "cb_usd": 0.4977, "ref_usd": 0.4977}, "DOT": {"up_krw": 1487.0, "bt_krw": 1485.0, "cb_usd": 0.9865, "ref_usd": 0.9865}, "UNI": {"up_krw": 3842.0, "bt_krw": 3837.0, "ref_usd": 2.53202}, "ICP": {"up_krw": 3702.0, "bt_krw": 3677.0, "ref_usd": 2.439754}, "SKY": {"up_krw": 84.8, "bt_krw": 84.82, "ref_usd": 0.055886}, "MORPHO": {"bt_krw": 2912.0, "ref_usd": 1.919115}, "PEPE": {"up_krw": 0.0043, "bt_krw": 0.0043, "ref_usd": 3e-06}, "ETC": {"up_krw": 10840.0, "bt_krw": 10860.0, "ref_usd": 7.14396}, "ATOM": {"up_krw": 2997.0, "bt_krw": 2998.0, "ref_usd": 1.975134}, "AAVE": {"up_krw": 100900.0, "bt_krw": 100800.0, "ref_usd": 66.49682}, "RENDER": {"up_krw": 2669.0, "bt_krw": 2650.0, "ref_usd": 1.758969}, "STABLE": {"bt_krw": 54.2, "ref_usd": 0.03572}, "DEXE": {"bt_krw": 26950.0, "ref_usd": 17.761044}, "VVV": {"up_krw": 26310.0, "bt_krw": 26030.0, "ref_usd": 17.33926}, "POL": {"up_krw": 113.0, "bt_krw": 112.0, "ref_usd": 0.074471}, "ALGO": {"up_krw": 134.0, "bt_krw": 134.0, "ref_usd": 0.088311}, "ENA": {"up_krw": 126.0, "bt_krw": 126.0, "ref_usd": 0.083039}, "FLR": {"bt_krw": 11.78, "ref_usd": 0.007763}, "JST": {"up_krw": 115.0, "bt_krw": 113.0, "ref_usd": 0.075789}, "FIL": {"up_krw": 1183.0, "bt_krw": 1194.0, "ref_usd": 0.779641}, "JUP": {"up_krw": 262.0, "bt_krw": 261.0, "ref_usd": 0.172668}, "APT": {"up_krw": 1012.0, "bt_krw": 1014.0, "ref_usd": 0.666945}, "ARB": {"up_krw": 130.0, "bt_krw": 130.0, "ref_usd": 0.085675}, "PUMP": {"up_krw": 2.33, "bt_krw": 2.299, "ref_usd": 0.001536}, "INJ": {"up_krw": 7935.0, "bt_krw": 7900.0, "ref_usd": 5.229458}, "TRUMP": {"up_krw": 3343.0, "bt_krw": 3343.0, "ref_usd": 2.20316}, "CAKE": {"bt_krw": 2009.0, "ref_usd": 1.324005}, "KITE": {"up_krw": 295.0, "bt_krw": 292.0, "ref_usd": 0.194416}, "FET": {"bt_krw": 302.0, "ref_usd": 0.199029}, "VET": {"up_krw": 7.76, "bt_krw": 7.753, "ref_usd": 0.005114}, "PENGU": {"up_krw": 10.3, "bt_krw": 10.25, "ref_usd": 0.006788}, "VIRTUAL": {"up_krw": 962.0, "bt_krw": 963.0, "ref_usd": 0.633993}, "H": {"bt_krw": 229.0, "ref_usd": 0.150919}, "BONK": {"up_krw": 0.00676, "bt_krw": 0.0067, "ref_usd": 4e-06}, "GWEI": {"bt_krw": 276.0, "ref_usd": 0.181894}, "SEI": {"up_krw": 82.2, "bt_krw": 82.06, "ref_usd": 0.054173}, "CRV": {"bt_krw": 358.0, "ref_usd": 0.235935}, "AERO": {"up_krw": 550.0, "bt_krw": 552.0, "ref_usd": 0.36247}, "STX": {"up_krw": 280.0, "bt_krw": 279.0, "ref_usd": 0.18453}, "SUN": {"up_krw": 25.6, "bt_krw": 25.24, "ref_usd": 0.016871}, "TIA": {"up_krw": 515.0, "bt_krw": 509.0, "ref_usd": 0.339404}, "PYTH": {"up_krw": 58.5, "bt_krw": 58.05, "ref_usd": 0.038554}, "GNO": {"bt_krw": 388700.0, "ref_usd": 256.167632}, "ETHFI": {"up_krw": 482.0, "bt_krw": 478.0, "ref_usd": 0.317656}, "CHZ": {"up_krw": 38.9, "bt_krw": 38.88, "ref_usd": 0.025637}, "NFT": {"bt_krw": 0.0004, "ref_usd": 0.0}, "JTO": {"up_krw": 821.0, "bt_krw": 821.0, "ref_usd": 0.541069}, "BTT": {"up_krw": 0.000403, "bt_krw": 0.0005, "ref_usd": 0.0}, "XTZ": {"up_krw": 361.0, "bt_krw": 361.0, "ref_usd": 0.237912}, "MON": {"up_krw": 32.6, "bt_krw": 32.38, "ref_usd": 0.021485}, "2Z": {"up_krw": 109.0, "bt_krw": 108.0, "ref_usd": 0.071835}, "FLOKI": {"bt_krw": 0.0379, "ref_usd": 2.5e-05}, "ZRO": {"up_krw": 1439.0, "bt_krw": 1427.0, "ref_usd": 0.948354}, "GRASS": {"bt_krw": 580.0, "ref_usd": 0.382241}, "BSV": {"up_krw": 17920.0, "bt_krw": 17800.0, "ref_usd": 11.809941}, "CFX": {"bt_krw": 67.98, "ref_usd": 0.044801}, "JASMY": {"bt_krw": 7.054, "ref_usd": 0.004649}, "OP": {"up_krw": 161.0, "bt_krw": 161.0, "ref_usd": 0.106105}, "PENDLE": {"up_krw": 2001.0, "bt_krw": 1984.0, "ref_usd": 1.318733}, "FF": {"up_krw": 118.0, "bt_krw": 117.0, "ref_usd": 0.077766}, "LDO": {"bt_krw": 393.0, "ref_usd": 0.259001}, "XPL": {"up_krw": 133.0, "bt_krw": 132.0, "ref_usd": 0.087652}, "STRK": {"bt_krw": 52.43, "ref_usd": 0.034553}, "GRT": {"up_krw": 30.3, "bt_krw": 30.0, "ref_usd": 0.019969}, "KAIA": {"bt_krw": 55.6, "ref_usd": 0.036642}, "IOTA": {"up_krw": 70.6, "bt_krw": 70.31, "ref_usd": 0.046528}, "ENS": {"up_krw": 7440.0, "bt_krw": 7460.0, "ref_usd": 4.903234}, "AKT": {"up_krw": 976.0, "bt_krw": 967.0, "ref_usd": 0.64322}, "PIEVERSE": {"up_krw": 988.0, "bt_krw": 977.0, "ref_usd": 0.651128}, "COMP": {"up_krw": 26700.0, "bt_krw": 26310.0, "ref_usd": 17.596284}, "BILL": {"bt_krw": 104.0, "ref_usd": 0.06854}, "AXS": {"up_krw": 1462.0, "bt_krw": 1458.0, "ref_usd": 0.963512}, "RAY": {"up_krw": 915.0, "bt_krw": 906.0, "ref_usd": 0.603019}, "WIF": {"up_krw": 246.0, "bt_krw": 243.0, "ref_usd": 0.162123}, "TRAC": {"up_krw": 544.0, "bt_krw": 537.0, "ref_usd": 0.358516}, "THETA": {"up_krw": 243.0, "bt_krw": 241.0, "ref_usd": 0.160146}}}]