[{"timestamp": "2026-04-17T02:41:22.071194+00:00", "usd_krw": 1478.12, "coins": {"BTC": {"up_krw": 110377000.0, "bt_krw": 110402000.0, "cb_usd": 74763.285, "ref_usd": 74763.285}, "ETH": {"up_krw": 3448000.0, "bt_krw": 3447000.0, "cb_usd": 2333.765, "ref_usd": 2333.765}, "USDT": {"up_krw": 1478.0, "bt_krw": 1477.0, "cb_usd": 1.000345, "ref_usd": 1.000345}, "XRP": {"up_krw": 2112.0, "bt_krw": 2111.0, "cb_usd": 1.42885, "ref_usd": 1.42885}, "BNB": {"bt_krw": 929000.0, "cb_usd": 630.155, "ref_usd": 630.155}, "USDC": {"up_krw": 1475.0, "bt_krw": 1478.0, "cb_usd": 1.0, "ref_usd": 1.0}, "SOL": {"up_krw": 130000.0, "bt_krw": 130000.0, "cb_usd": 87.965, "ref_usd": 87.965}, "TRX": {"up_krw": 482.0, "bt_krw": 484.0, "cb_usd": 0.3259528206973965, "ref_usd": 0.3259528206973965}, "DOGE": {"up_krw": 145.0, "bt_krw": 145.0, "cb_usd": 0.097855, "ref_usd": 0.097855}, "USDS": {"up_krw": 1472.0, "bt_krw": 1476.0, "cb_usd": 0.99985, "ref_usd": 0.99985}, "HYPE": {"cb_usd": 43.515, "ref_usd": 43.515}, "ADA": {"up_krw": 377.0, "bt_krw": 377.0, "cb_usd": 0.2554, "ref_usd": 0.2554}, "BCH": {"up_krw": 665000.0, "bt_krw": 666000.0, "cb_usd": 451.315, "ref_usd": 451.315}, "LINK": {"up_krw": 13940.0, "bt_krw": 13950.0, "cb_usd": 9.4535, "ref_usd": 9.4535}, "USDE": {"up_krw": 1482.0, "bt_krw": 1481.0, "cb_usd": 1.0002238035591986, "ref_usd": 1.0002238035591986}, "CC": {"up_krw": 218.0, "ref_usd": 0.147485}, "ZEC": {"cb_usd": 333.455, "ref_usd": 333.455}, "XLM": {"up_krw": 246.0, "bt_krw": 246.0, "cb_usd": 0.166627, "ref_usd": 0.166627}, "DAI": {"cb_usd": 0.9999, "ref_usd": 0.9999}, "LTC": {"cb_usd": 55.765, "ref_usd": 55.765}, "RAVE": {"cb_usd": 17.3476, "ref_usd": 17.3476}, "AVAX": {"up_krw": 14180.0, "bt_krw": 14200.0, "cb_usd": 9.615, "ref_usd": 9.615}, "USD1": {"up_krw": 1477.0, "bt_krw": 1479.0, "cb_usd": 0.99995, "ref_usd": 0.99995}, "PYUSD": {"cb_usd": 1.0, "ref_usd": 1.0}, "SUI": {"up_krw": 1461.0, "bt_krw": 1458.0, "cb_usd": 0.9888, "ref_usd": 0.9888}, "HBAR": {"up_krw": 132.0, "bt_krw": 132.0, "cb_usd": 0.08954, "ref_usd": 0.08954}, "SHIB": {"up_krw": 0.00911, "bt_krw": 0.0092, "cb_usd": 6.18e-06, "ref_usd": 6.18e-06}, "TON": {"bt_krw": 2095.0, "cb_usd": 1.4215, "ref_usd": 1.4215}, "CRO": {"up_krw": 104.0, "bt_krw": 104.0, "cb_usd": 0.070415, "ref_usd": 0.070415}, "XAUT": {"up_krw": 7046000.0, "bt_krw": 7041000.0, "ref_usd": 4766.864964}, "WLFI": {"up_krw": 119.0, "bt_krw": 120.0, "cb_usd": 0.08108, "ref_usd": 0.08108}, "BUIDL": {"cb_usd": 1.0, "ref_usd": 1.0}, "TAO": {"up_krw": 372500.0, "bt_krw": 371000.0, "cb_usd": 252.86, "ref_usd": 252.86}, "PAXG": {"bt_krw": 7051000.0, "cb_usd": 4776.725, "ref_usd": 4776.725}, "MNT": {"up_krw": 983.0, "bt_krw": 983.0, "ref_usd": 0.665034}, "DOT": {"up_krw": 1918.0, "bt_krw": 1922.0, "cb_usd": 1.301, "ref_usd": 1.301}, "UNI": {"up_krw": 5005.0, "bt_krw": 4968.0, "cb_usd": 3.3845, "ref_usd": 3.3845}, "NEAR": {"up_krw": 2089.0, "bt_krw": 2085.0, "cb_usd": 1.415, "ref_usd": 1.415}, "USDF": {"cb_usd": 1.0, "ref_usd": 1.0}, "SKY": {"up_krw": 112.0, "bt_krw": 113.0, "cb_usd": 0.076475, "ref_usd": 0.076475}, "AAVE": {"up_krw": 167900.0, "bt_krw": 167700.0, "ref_usd": 113.590211}, "ASTER": {"bt_krw": 1002.0, "ref_usd": 0.677888}, "PEPE": {"up_krw": 0.00582, "bt_krw": 0.0059, "ref_usd": 4e-06}, "ICP": {"up_krw": 3850.0, "bt_krw": 3841.0, "ref_usd": 2.604659}, "ETC": {"up_krw": 12750.0, "bt_krw": 12740.0, "ref_usd": 8.62582}, "ONDO": {"up_krw": 393.0, "bt_krw": 392.0, "ref_usd": 0.265878}, "PUMP": {"up_krw": 2.9, "bt_krw": 2.882, "ref_usd": 0.001962}, "WLD": {"up_krw": 468.0, "bt_krw": 471.0, "ref_usd": 0.316618}, "ALGO": {"up_krw": 170.0, "bt_krw": 171.0, "ref_usd": 0.115011}, "MORPHO": {"bt_krw": 2630.0, "ref_usd": 1.779287}, "RENDER": {"up_krw": 2778.0, "bt_krw": 2778.0, "ref_usd": 1.879414}, "ENA": {"up_krw": 164.0, "bt_krw": 164.0, "ref_usd": 0.110952}, "POL": {"up_krw": 132.0, "bt_krw": 133.0, "ref_usd": 0.089303}, "ATOM": {"up_krw": 2671.0, "bt_krw": 2672.0, "ref_usd": 1.807025}, "APT": {"up_krw": 1452.0, "bt_krw": 1448.0, "ref_usd": 0.982329}, "ARB": {"up_krw": 189.0, "bt_krw": 189.0, "ref_usd": 0.127865}, "FIL": {"up_krw": 1455.0, "bt_krw": 1453.0, "ref_usd": 0.984358}, "TRUMP": {"up_krw": 4475.0, "bt_krw": 4471.0, "ref_usd": 3.027494}, "FLR": {"bt_krw": 12.02, "ref_usd": 0.008132}, "JUP": {"up_krw": 270.0, "bt_krw": 269.0, "ref_usd": 0.182664}, "VET": {"up_krw": 10.8, "bt_krw": 10.76, "ref_usd": 0.007307}, "JST": {"up_krw": 100.0, "bt_krw": 99.99, "ref_usd": 0.067653}, "STABLE": {"bt_krw": 38.63, "ref_usd": 0.026135}, "BONK": {"up_krw": 0.00949, "bt_krw": 0.0095, "ref_usd": 6e-06}, "CAKE": {"bt_krw": 2387.0, "ref_usd": 1.614889}, "FET": {"bt_krw": 346.0, "ref_usd": 0.234081}, "DEXE": {"bt_krw": 16470.0, "ref_usd": 11.14253}, "ZRO": {"up_krw": 2885.0, "bt_krw": 2882.0, "ref_usd": 1.951803}, "PENGU": {"up_krw": 11.2, "bt_krw": 11.25, "ref_usd": 0.007577}, "VIRTUAL": {"up_krw": 1076.0, "bt_krw": 1075.0, "ref_usd": 0.727952}, "STX": {"up_krw": 354.0, "bt_krw": 353.0, "ref_usd": 0.239493}, "CHZ": {"up_krw": 61.5, "bt_krw": 61.55, "ref_usd": 0.041607}, "XTZ": {"up_krw": 547.0, "bt_krw": 547.0, "ref_usd": 0.370065}, "MON": {"up_krw": 50.1, "bt_krw": 50.1, "ref_usd": 0.033894}, "ETHFI": {"up_krw": 704.0, "bt_krw": 702.0, "ref_usd": 0.476281}, "VVV": {"bt_krw": 12650.0, "ref_usd": 8.558167}, "SEI": {"up_krw": 85.8, "bt_krw": 85.62, "ref_usd": 0.058047}, "TIA": {"up_krw": 603.0, "bt_krw": 605.0, "ref_usd": 0.407951}, "AERO": {"up_krw": 587.0, "bt_krw": 585.0, "ref_usd": 0.397126}, "LDO": {"bt_krw": 633.0, "ref_usd": 0.428247}, "SUN": {"up_krw": 27.3, "bt_krw": 27.22, "ref_usd": 0.018469}, "CFX": {"bt_krw": 99.14, "ref_usd": 0.067072}, "CRV": {"bt_krw": 343.0, "ref_usd": 0.232051}, "INJ": {"up_krw": 5050.0, "bt_krw": 5050.0, "ref_usd": 3.416501}, "NFT": {"bt_krw": 0.0004, "ref_usd": 0.0}, "2Z": {"up_krw": 139.0, "bt_krw": 139.0, "ref_usd": 0.094038}, "XPL": {"up_krw": 202.0, "bt_krw": 201.0, "ref_usd": 0.13666}, "BTT": {"up_krw": 0.000486, "bt_krw": 0.0005, "ref_usd": 0.0}, "BSV": {"up_krw": 23570.0, "bt_krw": 23470.0, "ref_usd": 15.945928}, "GNO": {"bt_krw": 176100.0, "ref_usd": 119.137797}, "FLOKI": {"bt_krw": 0.0468, "ref_usd": 3.2e-05}, "KITE": {"up_krw": 232.0, "bt_krw": 229.0, "ref_usd": 0.156956}, "SYRUP": {"up_krw": 356.0, "bt_krw": 359.0, "ref_usd": 0.240846}, "OP": {"up_krw": 193.0, "bt_krw": 193.0, "ref_usd": 0.130571}, "KAIA": {"bt_krw": 70.31, "ref_usd": 0.047567}, "JASMY": {"bt_krw": 8.316, "ref_usd": 0.005626}, "PYTH": {"up_krw": 70.7, "bt_krw": 70.81, "ref_usd": 0.047831}, "GRT": {"up_krw": 37.7, "bt_krw": 37.76, "ref_usd": 0.025505}, "IOTA": {"up_krw": 86.1, "bt_krw": 85.99, "ref_usd": 0.05825}, "ENS": {"up_krw": 9080.0, "bt_krw": 9060.0, "ref_usd": 6.142937}, "COMP": {"up_krw": 35600.0, "bt_krw": 35590.0, "ref_usd": 24.084643}, "IP": {"up_krw": 974.0, "bt_krw": 976.0, "ref_usd": 0.658945}, "SAND": {"up_krw": 122.0, "bt_krw": 122.0, "ref_usd": 0.082537}, "WIF": {"bt_krw": 316.0, "ref_usd": 0.213785}, "H": {"bt_krw": 171.0, "ref_usd": 0.115687}, "STRK": {"bt_krw": 53.29, "ref_usd": 0.036053}, "PENDLE": {"up_krw": 1872.0, "bt_krw": 1859.0, "ref_usd": 1.266473}, "NEO": {"up_krw": 4323.0, "bt_krw": 4338.0, "ref_usd": 2.92466}, "GRASS": {"bt_krw": 521.0, "ref_usd": 0.352475}, "AXS": {"up_krw": 1736.0, "bt_krw": 1732.0, "ref_usd": 1.174465}, "THETA": {"up_krw": 289.0, "bt_krw": 289.0, "ref_usd": 0.195519}, "RAY": {"up_krw": 1002.0, "bt_krw": 999.0, "ref_usd": 0.677888}, "MANA": {"up_krw": 138.0, "bt_krw": 137.0, "ref_usd": 0.093362}, "XCN": {"bt_krw": 7.025, "ref_usd": 0.004753}, "WAL": {"up_krw": 112.0, "bt_krw": 112.0, "ref_usd": 0.075772}, "FF": {"up_krw": 111.0, "bt_krw": 110.0, "ref_usd": 0.075095}, "S": {"bt_krw": 67.54, "ref_usd": 0.045693}}}, {"timestamp": "2026-04-17T13:22:57.123537+00:00", "usd_krw": 1478.12, "coins": {"BTC": {"up_krw": 112999000.0, "bt_krw": 112924000.0, "cb_usd": 76815.405, "ref_usd": 76815.405}, "ETH": {"up_krw": 3565000.0, "bt_krw": 3560000.0, "cb_usd": 2425.805, "ref_usd": 2425.805}, "USDT": {"up_krw": 1472.0, "bt_krw": 1470.0, "cb_usd": 1.000365, "ref_usd": 1.000365}, "XRP": {"up_krw": 2171.0, "bt_krw": 2169.0, "cb_usd": 1.47595, "ref_usd": 1.47595}, "BNB": {"bt_krw": 941000.0, "cb_usd": 640.97, "ref_usd": 640.97}, "USDC": {"up_krw": 1471.0, "bt_krw": 1470.0, "cb_usd": 1.0, "ref_usd": 1.0}, "SOL": {"up_krw": 132600.0, "bt_krw": 132400.0, "cb_usd": 90.07, "ref_usd": 90.07}, "TRX": {"up_krw": 477.0, "bt_krw": 477.0, "cb_usd": 0.324986022785023, "ref_usd": 0.324986022785023}, "DOGE": {"up_krw": 150.0, "bt_krw": 149.0, "cb_usd": 0.10122, "ref_usd": 0.10122}, "USDS": {"up_krw": 1475.0, "bt_krw": 1475.0, "cb_usd": 0.9997, "ref_usd": 0.9997}, "HYPE": {"cb_usd": 44.575, "ref_usd": 44.575}, "ADA": {"up_krw": 389.0, "bt_krw": 388.0, "cb_usd": 0.2638, "ref_usd": 0.2638}, "BCH": {"up_krw": 668500.0, "bt_krw": 667500.0, "cb_usd": 453.885, "ref_usd": 453.885}, "LINK": {"up_krw": 14360.0, "bt_krw": 14360.0, "cb_usd": 9.769, "ref_usd": 9.769}, "USDE": {"up_krw": 1470.0, "bt_krw": 1475.0, "cb_usd": 1.0002738461434657, "ref_usd": 1.0002738461434657}, "CC": {"up_krw": 222.0, "ref_usd": 0.150191}, "ZEC": {"cb_usd": 345.75, "ref_usd": 345.75}, "XLM": {"up_krw": 254.0, "bt_krw": 254.0, "cb_usd": 0.1722625, "ref_usd": 0.1722625}, "RAVE": {"cb_usd": 18.7977, "ref_usd": 18.7977}, "LTC": {"cb_usd": 57.22, "ref_usd": 57.22}, "DAI": {"cb_usd": 0.9999, "ref_usd": 0.9999}, "AVAX": {"up_krw": 14520.0, "bt_krw": 14500.0, "cb_usd": 9.875, "ref_usd": 9.875}, "USD1": {"up_krw": 1472.0, "bt_krw": 1471.0, "cb_usd": 1.00005, "ref_usd": 1.00005}, "PYUSD": {"cb_usd": 1.0, "ref_usd": 1.0}, "SUI": {"up_krw": 1506.0, "bt_krw": 1505.0, "cb_usd": 1.0246, "ref_usd": 1.0246}, "HBAR": {"up_krw": 137.0, "bt_krw": 137.0, "cb_usd": 0.093015, "ref_usd": 0.093015}, "SHIB": {"up_krw": 0.00943, "bt_krw": 0.0095, "cb_usd": 6.425e-06, "ref_usd": 6.425e-06}, "TON": {"bt_krw": 2079.0, "cb_usd": 1.42, "ref_usd": 1.42}, "CRO": {"up_krw": 105.0, "bt_krw": 106.0, "cb_usd": 0.07203, "ref_usd": 0.07203}, "XAUT": {"up_krw": 7117000.0, "bt_krw": 7093000.0, "ref_usd": 4814.898943}, "WLFI": {"up_krw": 122.0, "bt_krw": 123.0, "cb_usd": 0.08321, "ref_usd": 0.08321}, "BUIDL": {"cb_usd": 1.0, "ref_usd": 1.0}, "TAO": {"up_krw": 378300.0, "bt_krw": 376500.0, "cb_usd": 257.485, "ref_usd": 257.485}, "PAXG": {"bt_krw": 7116000.0, "cb_usd": 4842.58, "ref_usd": 4842.58}, "MNT": {"up_krw": 1015.0, "bt_krw": 1013.0, "ref_usd": 0.686683}, "DOT": {"up_krw": 1959.0, "bt_krw": 1958.0, "cb_usd": 1.331, "ref_usd": 1.331}, "UNI": {"up_krw": 5185.0, "bt_krw": 5165.0, "cb_usd": 3.52, "ref_usd": 3.52}, "NEAR": {"up_krw": 2087.0, "bt_krw": 2080.0, "cb_usd": 1.4165, "ref_usd": 1.4165}, "SKY": {"up_krw": 115.0, "bt_krw": 114.0, "cb_usd": 0.078215, "ref_usd": 0.078215}, "USDF": {"cb_usd": 1.0, "ref_usd": 1.0}, "AAVE": {"up_krw": 173500.0, "bt_krw": 173000.0, "ref_usd": 117.378807}, "ASTER": {"bt_krw": 1017.0, "ref_usd": 0.688036}, "PEPE": {"up_krw": 0.00595, "bt_krw": 0.006, "ref_usd": 4e-06}, "ICP": {"up_krw": 3916.0, "bt_krw": 3901.0, "ref_usd": 2.649311}, "ETC": {"up_krw": 13020.0, "bt_krw": 12990.0, "ref_usd": 8.808485}, "ONDO": {"up_krw": 402.0, "bt_krw": 402.0, "ref_usd": 0.271967}, "PUMP": {"up_krw": 3.04, "bt_krw": 3.029, "ref_usd": 0.002057}, "MORPHO": {"bt_krw": 2857.0, "ref_usd": 1.93286}, "ALGO": {"up_krw": 172.0, "bt_krw": 171.0, "ref_usd": 0.116364}, "WLD": {"up_krw": 464.0, "bt_krw": 466.0, "ref_usd": 0.313912}, "ENA": {"up_krw": 171.0, "bt_krw": 170.0, "ref_usd": 0.115687}, "RENDER": {"up_krw": 2833.0, "bt_krw": 2834.0, "ref_usd": 1.916623}, "POL": {"up_krw": 134.0, "bt_krw": 133.0, "ref_usd": 0.090656}, "ATOM": {"up_krw": 2721.0, "bt_krw": 2719.0, "ref_usd": 1.840851}, "ARB": {"up_krw": 201.0, "bt_krw": 200.0, "ref_usd": 0.135984}, "APT": {"up_krw": 1459.0, "bt_krw": 1456.0, "ref_usd": 0.987064}, "FIL": {"up_krw": 1486.0, "bt_krw": 1482.0, "ref_usd": 1.005331}, "FLR": {"bt_krw": 12.2, "ref_usd": 0.008254}, "TRUMP": {"up_krw": 4514.0, "bt_krw": 4512.0, "ref_usd": 3.053879}, "JUP": {"up_krw": 276.0, "bt_krw": 277.0, "ref_usd": 0.186724}, "VET": {"up_krw": 11.0, "bt_krw": 10.91, "ref_usd": 0.007442}, "BONK": {"up_krw": 0.00973, "bt_krw": 0.0098, "ref_usd": 7e-06}, "STABLE": {"bt_krw": 38.75, "ref_usd": 0.026216}, "DEXE": {"bt_krw": 17830.0, "ref_usd": 12.062617}, "JST": {"up_krw": 95.3, "bt_krw": 95.08, "ref_usd": 0.064474}, "CAKE": {"bt_krw": 2403.0, "ref_usd": 1.625713}, "FET": {"bt_krw": 350.0, "ref_usd": 0.236787}, "ZRO": {"up_krw": 2974.0, "bt_krw": 2969.0, "ref_usd": 2.012015}, "PENGU": {"up_krw": 11.9, "bt_krw": 11.8, "ref_usd": 0.008051}, "VIRTUAL": {"up_krw": 1137.0, "bt_krw": 1133.0, "ref_usd": 0.76922}, "STX": {"up_krw": 364.0, "bt_krw": 363.0, "ref_usd": 0.246259}, "CHZ": {"up_krw": 61.7, "bt_krw": 61.67, "ref_usd": 0.041742}, "MON": {"up_krw": 52.3, "bt_krw": 52.26, "ref_usd": 0.035383}, "VVV": {"bt_krw": 13460.0, "ref_usd": 9.10616}, "ETHFI": {"up_krw": 739.0, "bt_krw": 737.0, "ref_usd": 0.499959}, "XTZ": {"up_krw": 560.0, "bt_krw": 555.0, "ref_usd": 0.37886}, "SEI": {"up_krw": 87.7, "bt_krw": 87.41, "ref_usd": 0.059332}, "AERO": {"up_krw": 639.0, "bt_krw": 641.0, "ref_usd": 0.432306}, "TIA": {"up_krw": 595.0, "bt_krw": 595.0, "ref_usd": 0.402538}, "LDO": {"bt_krw": 630.0, "ref_usd": 0.426217}, "CRV": {"bt_krw": 356.0, "ref_usd": 0.240846}, "SUN": {"up_krw": 27.4, "bt_krw": 27.34, "ref_usd": 0.018537}, "INJ": {"up_krw": 5075.0, "bt_krw": 5075.0, "ref_usd": 3.433415}, "CFX": {"bt_krw": 95.86, "ref_usd": 0.064853}, "NFT": {"bt_krw": 0.0005, "ref_usd": 0.0}, "BSV": {"up_krw": 24290.0, "bt_krw": 24280.0, "ref_usd": 16.433033}, "XPL": {"up_krw": 201.0, "bt_krw": 200.0, "ref_usd": 0.135984}, "BTT": {"up_krw": 0.000487, "bt_krw": 0.0005, "ref_usd": 0.0}, "GNO": {"bt_krw": 181700.0, "ref_usd": 122.926393}, "2Z": {"up_krw": 137.0, "bt_krw": 136.0, "ref_usd": 0.092685}, "FLOKI": {"bt_krw": 0.0482, "ref_usd": 3.3e-05}, "KAIA": {"bt_krw": 75.0, "ref_usd": 0.05074}, "JASMY": {"bt_krw": 8.588, "ref_usd": 0.00581}, "OP": {"up_krw": 198.0, "bt_krw": 196.0, "ref_usd": 0.133954}, "PYTH": {"up_krw": 72.8, "bt_krw": 72.84, "ref_usd": 0.049252}, "SYRUP": {"up_krw": 360.0, "bt_krw": 361.0, "ref_usd": 0.243553}, "GRT": {"up_krw": 38.8, "bt_krw": 38.71, "ref_usd": 0.02625}, "KITE": {"up_krw": 220.0, "bt_krw": 218.0, "ref_usd": 0.148838}, "IOTA": {"up_krw": 89.5, "bt_krw": 89.01, "ref_usd": 0.06055}, "ENS": {"up_krw": 9325.0, "bt_krw": 9310.0, "ref_usd": 6.308688}, "COMP": {"up_krw": 36580.0, "bt_krw": 36400.0, "ref_usd": 24.747647}, "PENDLE": {"up_krw": 2040.0, "bt_krw": 2041.0, "ref_usd": 1.380131}, "SAND": {"up_krw": 125.0, "bt_krw": 125.0, "ref_usd": 0.084567}, "H": {"bt_krw": 180.0, "ref_usd": 0.121776}, "WIF": {"bt_krw": 323.0, "ref_usd": 0.218521}, "STRK": {"bt_krw": 54.93, "ref_usd": 0.037162}, "IP": {"up_krw": 887.0, "bt_krw": 887.0, "ref_usd": 0.600086}, "NEO": {"up_krw": 4457.0, "bt_krw": 4438.0, "ref_usd": 3.015316}, "GRASS": {"bt_krw": 554.0, "ref_usd": 0.3748}, "THETA": {"up_krw": 303.0, "bt_krw": 303.0, "ref_usd": 0.20499}, "AXS": {"up_krw": 1768.0, "bt_krw": 1763.0, "ref_usd": 1.196114}, "RAY": {"up_krw": 1039.0, "bt_krw": 1036.0, "ref_usd": 0.70292}, "MANA": {"up_krw": 142.0, "bt_krw": 141.0, "ref_usd": 0.096068}, "XCN": {"bt_krw": 7.195, "ref_usd": 0.004868}, "S": {"bt_krw": 69.0, "ref_usd": 0.046681}, "FF": {"up_krw": 111.0, "bt_krw": 110.0, "ref_usd": 0.075095}, "WAL": {"up_krw": 111.0, "bt_krw": 112.0, "ref_usd": 0.075095}, "GALA": {"bt_krw": 5.018, "ref_usd": 0.003395}}}]